Workbook

Sheet CBSMprovisões
A1: Data de lançamento | B1: Nº transação | C1: Origem | D1: Nº origem | E1: Ref.3 | F1: Conta de contrapartida | G1: Detalhes | H1: C/D (ML) | I1: Saldo acumulado (MC) | J1: Fornecedor | K1: SubGrupo | L1: Mês/Ano | M1: Empresa | N1: Descrição Conta
C2: SI | I2: 0
A3: 46022 | B3: 8635611 | C3: LC | D3: 8635611 | E3: F009096 | F3: 3313030 | G3: PROV. KRAKOWIAK ADVOGADOS - dez/25 | H3: -242060 | I3: -242060 | J3: =IF($A3="","",IFERROR(_xlfn.XLOOKUP($E3,cbsmfornecedor!$A:$A,cbsmfornecedor!$B:$B),"")) -> KRAKOWIAK ADVOGADOS | K3: =IF($A3="","",IFERROR(_xlfn.XLOOKUP($F3,cbsmpacote!$A:$A,cbsmpacote!$D:$D),"")) -> Services | L3: =IF($A3="","",DATE(YEAR($A3),MONTH($A3),1)) -> 45992 | M3: =IF($A3="","","CBSM") -> CBSM | N3: =IF($A3="","",IFERROR(_xlfn.XLOOKUP($F3,cbsmpacote!$A:$A,cbsmpacote!$B:$B),"")) -> Assessoria Jurídica
A4: 46022 | B4: 8635623 | C4: LC | D4: 8635623 | E4: F009582 | F4: 3313350 | G4: PROV. MENA INTELIGENCIA EM TALENTOS LTDA - dez/25 | H4: -10000 | I4: -252060 | J4: =IF($A4="","",IFERROR(_xlfn.XLOOKUP($E4,cbsmfornecedor!$A:$A,cbsmfornecedor!$B:$B),"")) -> MENA INTELIGENCIA EM TALENTOS LTDA | K4: =IF($A4="","",IFERROR(_xlfn.XLOOKUP($F4,cbsmpacote!$A:$A,cbsmpacote!$D:$D),"")) -> Services | L4: =IF($A4="","",DATE(YEAR($A4),MONTH($A4),1)) -> 45992 | M4: =IF($A4="","","CBSM") -> CBSM | N4: =IF($A4="","",IFERROR(_xlfn.XLOOKUP($F4,cbsmpacote!$A:$A,cbsmpacote!$B:$B),"")) -> Serviços de Consultoria
A5: 46052 | B5: 8652891 | C5: LC | D5: 8652891 | E5: F008870 | F5: 3313160 | G5: PROV. - PARLA CONTAC CENTER S/A - F008870 JAN26 | H5: -24000 | I5: -276060 | J5: =IF($A5="","",IFERROR(_xlfn.XLOOKUP($E5,cbsmfornecedor!$A:$A,cbsmfornecedor!$B:$B),"")) -> PARLA CONTAC CENTER S/A | K5: =IF($A5="","",IFERROR(_xlfn.XLOOKUP($F5,cbsmpacote!$A:$A,cbsmpacote!$D:$D),"")) -> CRM & Call Center | L5: =IF($A5="","",DATE(YEAR($A5),MONTH($A5),1)) -> 46023 | M5: =IF($A5="","","CBSM") -> CBSM | N5: =IF($A5="","",IFERROR(_xlfn.XLOOKUP($F5,cbsmpacote!$A:$A,cbsmpacote!$B:$B),"")) -> Despesas Call Center
A6: 46054 | B6: 8655981 | C6: LC | D6: 8655981 | E6: F009582 | F6: 3313350 | G6: PROV. MENA INTELIGENCIA EM TALENTOS LTDA - dez/25 (Estorno 8635623) | H6: 3551.56 | I6: -272508.44 | J6: =IF($A6="","",IFERROR(_xlfn.XLOOKUP($E6,cbsmfornecedor!$A:$A,cbsmfornecedor!$B:$B),"")) -> MENA INTELIGENCIA EM TALENTOS LTDA | K6: =IF($A6="","",IFERROR(_xlfn.XLOOKUP($F6,cbsmpacote!$A:$A,cbsmpacote!$D:$D),"")) -> Services | L6: =IF($A6="","",DATE(YEAR($A6),MONTH($A6),1)) -> 46054 | M6: =IF($A6="","","CBSM") -> CBSM | N6: =IF($A6="","",IFERROR(_xlfn.XLOOKUP($F6,cbsmpacote!$A:$A,cbsmpacote!$B:$B),"")) -> Serviços de Consultoria
A7: 46080 | B7: 8669549 | C7: LC | D7: 8669549 | E7: F008870 | F7: 3313160 | G7: PROV. PARLA CONTAC CENTER S/A - F008870 - FEV26 | H7: -24000 | I7: -296508.44 | J7: =IF($A7="","",IFERROR(_xlfn.XLOOKUP($E7,cbsmfornecedor!$A:$A,cbsmfornecedor!$B:$B),"")) -> PARLA CONTAC CENTER S/A | K7: =IF($A7="","",IFERROR(_xlfn.XLOOKUP($F7,cbsmpacote!$A:$A,cbsmpacote!$D:$D),"")) -> CRM & Call Center | L7: =IF($A7="","",DATE(YEAR($A7),MONTH($A7),1)) -> 46054 | M7: =IF($A7="","","CBSM") -> CBSM | N7: =IF($A7="","",IFERROR(_xlfn.XLOOKUP($F7,cbsmpacote!$A:$A,cbsmpacote!$B:$B),"")) -> Despesas Call Center
A8: 46112 | B8: 8686394 | C8: LC | D8: 8686394 | E8: F008408 | F8: 3313160 | G8: PROVISÃO 55TELECOM COMUNICAÇÃO LTDA - MARÇO 2026 | H8: -33100 | I8: -329608.44 | J8: =IF($A8="","",IFERROR(_xlfn.XLOOKUP($E8,cbsmfornecedor!$A:$A,cbsmfornecedor!$B:$B),"")) -> 55TELECOM COMUNICAÇÃO LTDA | K8: =IF($A8="","",IFERROR(_xlfn.XLOOKUP($F8,cbsmpacote!$A:$A,cbsmpacote!$D:$D),"")) -> CRM & Call Center | L8: =IF($A8="","",DATE(YEAR($A8),MONTH($A8),1)) -> 46082 | M8: =IF($A8="","","CBSM") -> CBSM | N8: =IF($A8="","",IFERROR(_xlfn.XLOOKUP($F8,cbsmpacote!$A:$A,cbsmpacote!$B:$B),"")) -> Despesas Call Center
A9: 46142 | B9: 8702918 | C9: LC | D9: 8702918 | E9: F005535 | F9: 3211020 | G9: PROV INFOBIP BRASIL SERVICOS DE VALOR ADICIONADO LTDA | H9: -78757.99 | I9: -408366.43 | J9: =IF($A9="","",IFERROR(_xlfn.XLOOKUP($E9,cbsmfornecedor!$A:$A,cbsmfornecedor!$B:$B),"")) -> INFOBIP BRAZIL SERVICOS DE VALOR ADICIONADO LTDA. | K9: =IF($A9="","",IFERROR(_xlfn.XLOOKUP($F9,cbsmpacote!$A:$A,cbsmpacote!$D:$D),"")) -> Other costs - CBSM CAT | L9: =IF($A9="","",DATE(YEAR($A9),MONTH($A9),1)) -> 46113 | M9: =IF($A9="","","CBSM") -> CBSM | N9: =IF($A9="","",IFERROR(_xlfn.XLOOKUP($F9,cbsmpacote!$A:$A,cbsmpacote!$B:$B),"")) -> CAT - Gastos com tecnologia
A10: 46142 | B10: 8702919 | C10: LC | D10: 8702919 | E10: F005535 | F10: 3211020 | G10: PROV INFOBIP BRASIL SERVICOS DE VALOR ADICIONADO LTDA | H10: -45331.47 | I10: -453697.9 | J10: =IF($A10="","",IFERROR(_xlfn.XLOOKUP($E10,cbsmfornecedor!$A:$A,cbsmfornecedor!$B:$B),"")) -> INFOBIP BRAZIL SERVICOS DE VALOR ADICIONADO LTDA. | K10: =IF($A10="","",IFERROR(_xlfn.XLOOKUP($F10,cbsmpacote!$A:$A,cbsmpacote!$D:$D),"")) -> Other costs - CBSM CAT | L10: =IF($A10="","",DATE(YEAR($A10),MONTH($A10),1)) -> 46113 | M10: =IF($A10="","","CBSM") -> CBSM | N10: =IF($A10="","",IFERROR(_xlfn.XLOOKUP($F10,cbsmpacote!$A:$A,cbsmpacote!$B:$B),"")) -> CAT - Gastos com tecnologia
A11: 46171 | B11: 8718557 | C11: LC | D11: 8718557 | E11: F006557 | F11: 3313030 | G11: Provisão MMF e A&F Créditos Previdenciários | H11: -59573.47 | I11: -513271.37 | J11: =IF($A11="","",IFERROR(_xlfn.XLOOKUP($E11,cbsmfornecedor!$A:$A,cbsmfornecedor!$B:$B),"")) -> MOSS, MUZZI, FALCAO, MASSOTE E WERNECK ADVOGADOS ASSOCIADOS | K11: =IF($A11="","",IFERROR(_xlfn.XLOOKUP($F11,cbsmpacote!$A:$A,cbsmpacote!$D:$D),"")) -> Services | L11: =IF($A11="","",DATE(YEAR($A11),MONTH($A11),1)) -> 46143 | M11: =IF($A11="","","CBSM") -> CBSM | N11: =IF($A11="","",IFERROR(_xlfn.XLOOKUP($F11,cbsmpacote!$A:$A,cbsmpacote!$B:$B),"")) -> Assessoria Jurídica
A12: 46171 | B12: 8719033 | C12: LC | D12: 8719033 | E12: F009633 | F12: 3313160 | G12: PROV. CSU S.A - F009633 | H12: -58405.53 | I12: -571676.9 | J12: =IF($A12="","",IFERROR(_xlfn.XLOOKUP($E12,cbsmfornecedor!$A:$A,cbsmfornecedor!$B:$B),"")) -> CSU DIGITAL | K12: =IF($A12="","",IFERROR(_xlfn.XLOOKUP($F12,cbsmpacote!$A:$A,cbsmpacote!$D:$D),"")) -> CRM & Call Center | L12: =IF($A12="","",DATE(YEAR($A12),MONTH($A12),1)) -> 46143 | M12: =IF($A12="","","CBSM") -> CBSM | N12: =IF($A12="","",IFERROR(_xlfn.XLOOKUP($F12,cbsmpacote!$A:$A,cbsmpacote!$B:$B),"")) -> Despesas Call Center
A13: 46171 | B13: 8719034 | C13: LC | D13: 8719034 | E13: F008408 | F13: 3313160 | G13: PROV. 55TELECOM COMUNICAÇÃO LTDA - F008408 | H13: -8847.57 | I13: -580524.47 | J13: =IF($A13="","",IFERROR(_xlfn.XLOOKUP($E13,cbsmfornecedor!$A:$A,cbsmfornecedor!$B:$B),"")) -> 55TELECOM COMUNICAÇÃO LTDA | K13: =IF($A13="","",IFERROR(_xlfn.XLOOKUP($F13,cbsmpacote!$A:$A,cbsmpacote!$D:$D),"")) -> CRM & Call Center | L13: =IF($A13="","",DATE(YEAR($A13),MONTH($A13),1)) -> 46143 | M13: =IF($A13="","","CBSM") -> CBSM | N13: =IF($A13="","",IFERROR(_xlfn.XLOOKUP($F13,cbsmpacote!$A:$A,cbsmpacote!$B:$B),"")) -> Despesas Call Center
A14: 46171 | B14: 8719035 | C14: LC | D14: 8719035 | E14: F008547 | F14: 3313161 | G14: PROV. QUEST TECNOLOGIA LTDA - F008547 | H14: -10500 | I14: -591024.47 | J14: =IF($A14="","",IFERROR(_xlfn.XLOOKUP($E14,cbsmfornecedor!$A:$A,cbsmfornecedor!$B:$B),"")) -> QUEST TECNOLOGIA LTDA | K14: =IF($A14="","",IFERROR(_xlfn.XLOOKUP($F14,cbsmpacote!$A:$A,cbsmpacote!$D:$D),"")) -> CRM & Call Center | L14: =IF($A14="","",DATE(YEAR($A14),MONTH($A14),1)) -> 46143 | M14: =IF($A14="","","CBSM") -> CBSM | N14: =IF($A14="","",IFERROR(_xlfn.XLOOKUP($F14,cbsmpacote!$A:$A,cbsmpacote!$B:$B),"")) -> Pesquisa
... A30: 46171 | B30: 8719257 | C30: LC | D30: 8719257 | E30: F009635 | F30: 3313380 | G30: PROV. ENYGMA TECNOLOGIA EM INFORMATICA LTDA | H30: -15400 | I30: -1358729.6 | J30: =IF($A30="","",IFERROR(_xlfn.XLOOKUP($E30,cbsmfornecedor!$A:$A,cbsmfornecedor!$B:$B),"")) -> ENYGMA TECNOLOGIA EM INFORMATICA LTDA | K30: =IF($A30="","",IFERROR(_xlfn.XLOOKUP($F30,cbsmpacote!$A:$A,cbsmpacote!$D:$D),"")) -> IT & Telecom | L30: =IF($A30="","",DATE(YEAR($A30),MONTH($A30),1)) -> 46143 | M30: =IF($A30="","","CBSM") -> CBSM | N30: =IF($A30="","",IFERROR(_xlfn.XLOOKUP($F30,cbsmpacote!$A:$A,cbsmpacote!$B:$B),"")) -> Suporte Técnico
J32: =IF($A32="","",IFERROR(_xlfn.XLOOKUP($E32,cbsmfornecedor!$A:$A,cbsmfornecedor!$B:$B),"")) | K32: =IF($A32="","",IFERROR(_xlfn.XLOOKUP($F32,cbsmpacote!$A:$A,cbsmpacote!$D:$D),"")) | L32: =IF($A32="","",DATE(YEAR($A32),MONTH($A32),1)) | M32: =IF($A32="","","CBSM") | N32: =IF($A32="","",IFERROR(_xlfn.XLOOKUP($F32,cbsmpacote!$A:$A,cbsmpacote!$B:$B),""))
J33: =IF($A33="","",IFERROR(_xlfn.XLOOKUP($E33,cbsmfornecedor!$A:$A,cbsmfornecedor!$B:$B),"")) | K33: =IF($A33="","",IFERROR(_xlfn.XLOOKUP($F33,cbsmpacote!$A:$A,cbsmpacote!$D:$D),"")) | L33: =IF($A33="","",DATE(YEAR($A33),MONTH($A33),1)) | M33: =IF($A33="","","CBSM") | N33: =IF($A33="","",IFERROR(_xlfn.XLOOKUP($F33,cbsmpacote!$A:$A,cbsmpacote!$B:$B),""))
J34: =IF($A34="","",IFERROR(_xlfn.XLOOKUP($E34,cbsmfornecedor!$A:$A,cbsmfornecedor!$B:$B),"")) | K34: =IF($A34="","",IFERROR(_xlfn.XLOOKUP($F34,cbsmpacote!$A:$A,cbsmpacote!$D:$D),"")) | L34: =IF($A34="","",DATE(YEAR($A34),MONTH($A34),1)) | M34: =IF($A34="","","CBSM") | N34: =IF($A34="","",IFERROR(_xlfn.XLOOKUP($F34,cbsmpacote!$A:$A,cbsmpacote!$B:$B),""))
J35: =IF($A35="","",IFERROR(_xlfn.XLOOKUP($E35,cbsmfornecedor!$A:$A,cbsmfornecedor!$B:$B),"")) | K35: =IF($A35="","",IFERROR(_xlfn.XLOOKUP($F35,cbsmpacote!$A:$A,cbsmpacote!$D:$D),"")) | L35: =IF($A35="","",DATE(YEAR($A35),MONTH($A35),1)) | M35: =IF($A35="","","CBSM") | N35: =IF($A35="","",IFERROR(_xlfn.XLOOKUP($F35,cbsmpacote!$A:$A,cbsmpacote!$B:$B),""))
J36: =IF($A36="","",IFERROR(_xlfn.XLOOKUP($E36,cbsmfornecedor!$A:$A,cbsmfornecedor!$B:$B),"")) | K36: =IF($A36="","",IFERROR(_xlfn.XLOOKUP($F36,cbsmpacote!$A:$A,cbsmpacote!$D:$D),"")) | L36: =IF($A36="","",DATE(YEAR($A36),MONTH($A36),1)) | M36: =IF($A36="","","CBSM") | N36: =IF($A36="","",IFERROR(_xlfn.XLOOKUP($F36,cbsmpacote!$A:$A,cbsmpacote!$B:$B),""))
J37: =IF($A37="","",IFERROR(_xlfn.XLOOKUP($E37,cbsmfornecedor!$A:$A,cbsmfornecedor!$B:$B),"")) | K37: =IF($A37="","",IFERROR(_xlfn.XLOOKUP($F37,cbsmpacote!$A:$A,cbsmpacote!$D:$D),"")) | L37: =IF($A37="","",DATE(YEAR($A37),MONTH($A37),1)) | M37: =IF($A37="","","CBSM") | N37: =IF($A37="","",IFERROR(_xlfn.XLOOKUP($F37,cbsmpacote!$A:$A,cbsmpacote!$B:$B),""))
J38: =IF($A38="","",IFERROR(_xlfn.XLOOKUP($E38,cbsmfornecedor!$A:$A,cbsmfornecedor!$B:$B),"")) | K38: =IF($A38="","",IFERROR(_xlfn.XLOOKUP($F38,cbsmpacote!$A:$A,cbsmpacote!$D:$D),"")) | L38: =IF($A38="","",DATE(YEAR($A38),MONTH($A38),1)) | M38: =IF($A38="","","CBSM") | N38: =IF($A38="","",IFERROR(_xlfn.XLOOKUP($F38,cbsmpacote!$A:$A,cbsmpacote!$B:$B),""))
J39: =IF($A39="","",IFERROR(_xlfn.XLOOKUP($E39,cbsmfornecedor!$A:$A,cbsmfornecedor!$B:$B),"")) | K39: =IF($A39="","",IFERROR(_xlfn.XLOOKUP($F39,cbsmpacote!$A:$A,cbsmpacote!$D:$D),"")) | L39: =IF($A39="","",DATE(YEAR($A39),MONTH($A39),1)) | M39: =IF($A39="","","CBSM") | N39: =IF($A39="","",IFERROR(_xlfn.XLOOKUP($F39,cbsmpacote!$A:$A,cbsmpacote!$B:$B),""))
J40: =IF($A40="","",IFERROR(_xlfn.XLOOKUP($E40,cbsmfornecedor!$A:$A,cbsmfornecedor!$B:$B),"")) | K40: =IF($A40="","",IFERROR(_xlfn.XLOOKUP($F40,cbsmpacote!$A:$A,cbsmpacote!$D:$D),"")) | L40: =IF($A40="","",DATE(YEAR($A40),MONTH($A40),1)) | M40: =IF($A40="","","CBSM") | N40: =IF($A40="","",IFERROR(_xlfn.XLOOKUP($F40,cbsmpacote!$A:$A,cbsmpacote!$B:$B),""))
J41: =IF($A41="","",IFERROR(_xlfn.XLOOKUP($E41,cbsmfornecedor!$A:$A,cbsmfornecedor!$B:$B),"")) | K41: =IF($A41="","",IFERROR(_xlfn.XLOOKUP($F41,cbsmpacote!$A:$A,cbsmpacote!$D:$D),"")) | L41: =IF($A41="","",DATE(YEAR($A41),MONTH($A41),1)) | M41: =IF($A41="","","CBSM") | N41: =IF($A41="","",IFERROR(_xlfn.XLOOKUP($F41,cbsmpacote!$A:$A,cbsmpacote!$B:$B),""))
J42: =IF($A42="","",IFERROR(_xlfn.XLOOKUP($E42,cbsmfornecedor!$A:$A,cbsmfornecedor!$B:$B),"")) | K42: =IF($A42="","",IFERROR(_xlfn.XLOOKUP($F42,cbsmpacote!$A:$A,cbsmpacote!$D:$D),"")) | L42: =IF($A42="","",DATE(YEAR($A42),MONTH($A42),1)) | M42: =IF($A42="","","CBSM") | N42: =IF($A42="","",IFERROR(_xlfn.XLOOKUP($F42,cbsmpacote!$A:$A,cbsmpacote!$B:$B),""))
J43: =IF($A43="","",IFERROR(_xlfn.XLOOKUP($E43,cbsmfornecedor!$A:$A,cbsmfornecedor!$B:$B),"")) | K43: =IF($A43="","",IFERROR(_xlfn.XLOOKUP($F43,cbsmpacote!$A:$A,cbsmpacote!$D:$D),"")) | L43: =IF($A43="","",DATE(YEAR($A43),MONTH($A43),1)) | M43: =IF($A43="","","CBSM") | N43: =IF($A43="","",IFERROR(_xlfn.XLOOKUP($F43,cbsmpacote!$A:$A,cbsmpacote!$B:$B),""))
... J200: =IF($A200="","",IFERROR(_xlfn.XLOOKUP($E200,cbsmfornecedor!$A:$A,cbsmfornecedor!$B:$B),"")) | K200: =IF($A200="","",IFERROR(_xlfn.XLOOKUP($F200,cbsmpacote!$A:$A,cbsmpacote!$D:$D),"")) | L200: =IF($A200="","",DATE(YEAR($A200),MONTH($A200),1)) | M200: =IF($A200="","","CBSM") | N200: =IF($A200="","",IFERROR(_xlfn.XLOOKUP($F200,cbsmpacote!$A:$A,cbsmpacote!$B:$B),""))

Sheet Noverdeprovisões
A1: Data de lançamento | B1: Nº transação | C1: Origem | D1: Nº origem | E1: Ref.3 | F1: Conta de contrapartida | G1: Detalhes | H1: C/D (ML) | I1: Saldo acumulado (MC) | J1: Fornecedor | K1: SubGrupo | L1: Mês/Ano | M1: Empresa | N1: Descrição Conta
C2: SI | I2: 0
A3: 45989 | B3: 17345 | C3: LC | D3: 17345 | E3: F000034 | F3: 81763005005 | G3: PROV. BOA VISTA SERVICOS S.A. - nov/25 | H3: -30000 | I3: -30000 | J3: =IF($A3="","",IFERROR(_xlfn.XLOOKUP($E3,noverdefornecedor!$A:$A,noverdefornecedor!$B:$B),"")) -> BOA VISTA SERVICOS S.A. | K3: =IF($A3="","",IFERROR(_xlfn.XLOOKUP($F3,noverdepacote!$A:$A,noverdepacote!$D:$D),"")) -> Other costs - NoVerde | L3: =IF($A3="","",DATE(YEAR($A3),MONTH($A3),1)) -> 45962 | M3: =IF($A3="","","Noverde") -> Noverde | N3: =IF($A3="","",IFERROR(_xlfn.XLOOKUP($F3,noverdepacote!$A:$A,noverdepacote!$B:$B),"")) -> Custo de Cobrança (Custo)
A4: 46022 | B4: 17852 | C4: LC | D4: 17852 | E4: F000034 | F4: 81763005005 | G4: PROV. BOA VISTA SERVICOS S.A. - dez/25 | H4: -30000 | I4: -60000 | J4: =IF($A4="","",IFERROR(_xlfn.XLOOKUP($E4,noverdefornecedor!$A:$A,noverdefornecedor!$B:$B),"")) -> BOA VISTA SERVICOS S.A. | K4: =IF($A4="","",IFERROR(_xlfn.XLOOKUP($F4,noverdepacote!$A:$A,noverdepacote!$D:$D),"")) -> Other costs - NoVerde | L4: =IF($A4="","",DATE(YEAR($A4),MONTH($A4),1)) -> 45992 | M4: =IF($A4="","","Noverde") -> Noverde | N4: =IF($A4="","",IFERROR(_xlfn.XLOOKUP($F4,noverdepacote!$A:$A,noverdepacote!$B:$B),"")) -> Custo de Cobrança (Custo)
A5: 46052 | B5: 18451 | C5: LC | D5: 18451 | E5: F000072 | F5: 81745009011 | G5: PROV. SERASA S.A - jan/26 | H5: -271400 | I5: -331400 | J5: =IF($A5="","",IFERROR(_xlfn.XLOOKUP($E5,noverdefornecedor!$A:$A,noverdefornecedor!$B:$B),"")) -> SERASA S.A | K5: =IF($A5="","",IFERROR(_xlfn.XLOOKUP($F5,noverdepacote!$A:$A,noverdepacote!$D:$D),"")) -> Other costs - NoVerde | L5: =IF($A5="","",DATE(YEAR($A5),MONTH($A5),1)) -> 46023 | M5: =IF($A5="","","Noverde") -> Noverde | N5: =IF($A5="","",IFERROR(_xlfn.XLOOKUP($F5,noverdepacote!$A:$A,noverdepacote!$B:$B),"")) -> Custo de Marketing (Custo)
A6: 46052 | B6: 18465 | C6: LC | D6: 18465 | E6: F000034 | F6: 81763005005 | G6: PROV. BOA VISTA SERVICOS S.A. - jan/26 | H6: -30000 | I6: -361400 | J6: =IF($A6="","",IFERROR(_xlfn.XLOOKUP($E6,noverdefornecedor!$A:$A,noverdefornecedor!$B:$B),"")) -> BOA VISTA SERVICOS S.A. | K6: =IF($A6="","",IFERROR(_xlfn.XLOOKUP($F6,noverdepacote!$A:$A,noverdepacote!$D:$D),"")) -> Other costs - NoVerde | L6: =IF($A6="","",DATE(YEAR($A6),MONTH($A6),1)) -> 46023 | M6: =IF($A6="","","Noverde") -> Noverde | N6: =IF($A6="","",IFERROR(_xlfn.XLOOKUP($F6,noverdepacote!$A:$A,noverdepacote!$B:$B),"")) -> Custo de Cobrança (Custo)
A7: 46080 | B7: 18971 | C7: LC | D7: 18971 | E7: F000034 | F7: 81763005006 | G7: PROV. BOA VISTA SERVICOS S.A. - fev/26 | H7: -250000 | I7: -611400 | J7: =IF($A7="","",IFERROR(_xlfn.XLOOKUP($E7,noverdefornecedor!$A:$A,noverdefornecedor!$B:$B),"")) -> BOA VISTA SERVICOS S.A. | K7: =IF($A7="","",IFERROR(_xlfn.XLOOKUP($F7,noverdepacote!$A:$A,noverdepacote!$D:$D),"")) -> Other costs - NoVerde | L7: =IF($A7="","",DATE(YEAR($A7),MONTH($A7),1)) -> 46054 | M7: =IF($A7="","","Noverde") -> Noverde | N7: =IF($A7="","",IFERROR(_xlfn.XLOOKUP($F7,noverdepacote!$A:$A,noverdepacote!$B:$B),"")) -> Custos de Credito
A8: 46080 | B8: 18997 | C8: LC | D8: 18997 | E8: F000034 | F8: 81763005005 | G8: PROV. BOA VISTA SERVICOS S.A. - F000034 - FEV26 | H8: -30000 | I8: -641400 | J8: =IF($A8="","",IFERROR(_xlfn.XLOOKUP($E8,noverdefornecedor!$A:$A,noverdefornecedor!$B:$B),"")) -> BOA VISTA SERVICOS S.A. | K8: =IF($A8="","",IFERROR(_xlfn.XLOOKUP($F8,noverdepacote!$A:$A,noverdepacote!$D:$D),"")) -> Other costs - NoVerde | L8: =IF($A8="","",DATE(YEAR($A8),MONTH($A8),1)) -> 46054 | M8: =IF($A8="","","Noverde") -> Noverde | N8: =IF($A8="","",IFERROR(_xlfn.XLOOKUP($F8,noverdepacote!$A:$A,noverdepacote!$B:$B),"")) -> Custo de Cobrança (Custo)
A9: 46080 | B9: 18998 | C9: LC | D9: 18998 | E9: F000132 | F9: 81763005005 | G9: PROV. Gestora de Inteligência de Crédito S.A. - F000132 - FEV26 | H9: -30000 | I9: -671400 | J9: =IF($A9="","",IFERROR(_xlfn.XLOOKUP($E9,noverdefornecedor!$A:$A,noverdefornecedor!$B:$B),"")) -> Gestora de Inteligência de Crédito S.A. | K9: =IF($A9="","",IFERROR(_xlfn.XLOOKUP($F9,noverdepacote!$A:$A,noverdepacote!$D:$D),"")) -> Other costs - NoVerde | L9: =IF($A9="","",DATE(YEAR($A9),MONTH($A9),1)) -> 46054 | M9: =IF($A9="","","Noverde") -> Noverde | N9: =IF($A9="","",IFERROR(_xlfn.XLOOKUP($F9,noverdepacote!$A:$A,noverdepacote!$B:$B),"")) -> Custo de Cobrança (Custo)
A10: 46112 | B10: 19656 | C10: LC | D10: 19656 | E10: F000102 | F10: 81757104017 | G10: PROVISÃO PARLA CONTACT CENTER S.A. - MARÇO 2026 | H10: -32695.94 | I10: -704095.94 | J10: =IF($A10="","",IFERROR(_xlfn.XLOOKUP($E10,noverdefornecedor!$A:$A,noverdefornecedor!$B:$B),"")) -> PARLA CONTACT CENTER S.A. | K10: =IF($A10="","",IFERROR(_xlfn.XLOOKUP($F10,noverdepacote!$A:$A,noverdepacote!$D:$D),"")) -> CRM & Call Center | L10: =IF($A10="","",DATE(YEAR($A10),MONTH($A10),1)) -> 46082 | M10: =IF($A10="","","Noverde") -> Noverde | N10: =IF($A10="","",IFERROR(_xlfn.XLOOKUP($F10,noverdepacote!$A:$A,noverdepacote!$B:$B),"")) -> Call Center
A11: 46112 | B11: 19672 | C11: LC | D11: 19672 | E11: F000145 | F11: 81763005005 | G11: PROV. PONTAL SERVICOS EM COMUNICACAO DIGITAL LTDA - mar/26 | H11: -250000 | I11: -954095.94 | J11: =IF($A11="","",IFERROR(_xlfn.XLOOKUP($E11,noverdefornecedor!$A:$A,noverdefornecedor!$B:$B),"")) -> PONTAL SERVICOS EM COMUNICACAO DIGITAL LTDA | K11: =IF($A11="","",IFERROR(_xlfn.XLOOKUP($F11,noverdepacote!$A:$A,noverdepacote!$D:$D),"")) -> Other costs - NoVerde | L11: =IF($A11="","",DATE(YEAR($A11),MONTH($A11),1)) -> 46082 | M11: =IF($A11="","","Noverde") -> Noverde | N11: =IF($A11="","",IFERROR(_xlfn.XLOOKUP($F11,noverdepacote!$A:$A,noverdepacote!$B:$B),"")) -> Custo de Cobrança (Custo)
A12: 46142 | B12: 20161 | C12: LC | D12: 20161 | E12: F000034 | F12: 81763005006 | G12: PROV BOA VISTA SERVICOS S.A. - F000034 | H12: -250000 | I12: -1204095.9 | J12: =IF($A12="","",IFERROR(_xlfn.XLOOKUP($E12,noverdefornecedor!$A:$A,noverdefornecedor!$B:$B),"")) -> BOA VISTA SERVICOS S.A. | K12: =IF($A12="","",IFERROR(_xlfn.XLOOKUP($F12,noverdepacote!$A:$A,noverdepacote!$D:$D),"")) -> Other costs - NoVerde | L12: =IF($A12="","",DATE(YEAR($A12),MONTH($A12),1)) -> 46113 | M12: =IF($A12="","","Noverde") -> Noverde | N12: =IF($A12="","",IFERROR(_xlfn.XLOOKUP($F12,noverdepacote!$A:$A,noverdepacote!$B:$B),"")) -> Custos de Credito
A13: 46142 | B13: 20177 | C13: LC | D13: 20177 | E13: F000159 | F13: 81763005005 | G13: PROV NEGOCIE AGORA SERVIÇOS E COBRANÇA LTDA - F000159 | H13: -5400 | I13: -1209495.9 | J13: =IF($A13="","",IFERROR(_xlfn.XLOOKUP($E13,noverdefornecedor!$A:$A,noverdefornecedor!$B:$B),"")) -> NEGOCIE AGORA SERVIÇOS E COBRANÇA LTDA | K13: =IF($A13="","",IFERROR(_xlfn.XLOOKUP($F13,noverdepacote!$A:$A,noverdepacote!$D:$D),"")) -> Other costs - NoVerde | L13: =IF($A13="","",DATE(YEAR($A13),MONTH($A13),1)) -> 46113 | M13: =IF($A13="","","Noverde") -> Noverde | N13: =IF($A13="","",IFERROR(_xlfn.XLOOKUP($F13,noverdepacote!$A:$A,noverdepacote!$B:$B),"")) -> Custo de Cobrança (Custo)
A14: 46142 | B14: 20181 | C14: LC | D14: 20181 | E14: F000029 | F14: 81763005007 | G14: PROV CLEAR SALE S.A. - F000029 | H14: -23000 | I14: -1232495.9 | J14: =IF($A14="","",IFERROR(_xlfn.XLOOKUP($E14,noverdefornecedor!$A:$A,noverdefornecedor!$B:$B),"")) -> CLEAR SALE S.A. | K14: =IF($A14="","",IFERROR(_xlfn.XLOOKUP($F14,noverdepacote!$A:$A,noverdepacote!$D:$D),"")) -> Other costs - NoVerde | L14: =IF($A14="","",DATE(YEAR($A14),MONTH($A14),1)) -> 46113 | M14: =IF($A14="","","Noverde") -> Noverde | N14: =IF($A14="","",IFERROR(_xlfn.XLOOKUP($F14,noverdepacote!$A:$A,noverdepacote!$B:$B),"")) -> Custo De Prevenção de Fraudes
... A36: 46173 | B36: 20769 | C36: LC | D36: 20769 | E36: LC00009 | F36: 81999006002 | G36: Recompra de Carteira FIDC - PERDA OPERACIONAL | H36: -600000 | I36: -4192101.4 | J36: =IF($A36="","",IFERROR(_xlfn.XLOOKUP($E36,noverdefornecedor!$A:$A,noverdefornecedor!$B:$B),"")) -> FIDC - PERDA OPERACIONAL | K36: =IF($A36="","",IFERROR(_xlfn.XLOOKUP($F36,noverdepacote!$A:$A,noverdepacote!$D:$D),"")) -> Financial Losses over Cyber attacks | L36: =IF($A36="","",DATE(YEAR($A36),MONTH($A36),1)) -> 46143 | M36: =IF($A36="","","Noverde") -> Noverde | N36: =IF($A36="","",IFERROR(_xlfn.XLOOKUP($F36,noverdepacote!$A:$A,noverdepacote!$B:$B),"")) -> Perdas Financeiras
J37: =IF($A37="","",IFERROR(_xlfn.XLOOKUP($E37,noverdefornecedor!$A:$A,noverdefornecedor!$B:$B),"")) | K37: =IF($A37="","",IFERROR(_xlfn.XLOOKUP($F37,noverdepacote!$A:$A,noverdepacote!$D:$D),"")) | L37: =IF($A37="","",DATE(YEAR($A37),MONTH($A37),1)) | M37: =IF($A37="","","Noverde") | N37: =IF($A37="","",IFERROR(_xlfn.XLOOKUP($F37,noverdepacote!$A:$A,noverdepacote!$B:$B),""))
J38: =IF($A38="","",IFERROR(_xlfn.XLOOKUP($E38,noverdefornecedor!$A:$A,noverdefornecedor!$B:$B),"")) | K38: =IF($A38="","",IFERROR(_xlfn.XLOOKUP($F38,noverdepacote!$A:$A,noverdepacote!$D:$D),"")) | L38: =IF($A38="","",DATE(YEAR($A38),MONTH($A38),1)) | M38: =IF($A38="","","Noverde") | N38: =IF($A38="","",IFERROR(_xlfn.XLOOKUP($F38,noverdepacote!$A:$A,noverdepacote!$B:$B),""))
J39: =IF($A39="","",IFERROR(_xlfn.XLOOKUP($E39,noverdefornecedor!$A:$A,noverdefornecedor!$B:$B),"")) | K39: =IF($A39="","",IFERROR(_xlfn.XLOOKUP($F39,noverdepacote!$A:$A,noverdepacote!$D:$D),"")) | L39: =IF($A39="","",DATE(YEAR($A39),MONTH($A39),1)) | M39: =IF($A39="","","Noverde") | N39: =IF($A39="","",IFERROR(_xlfn.XLOOKUP($F39,noverdepacote!$A:$A,noverdepacote!$B:$B),""))
J40: =IF($A40="","",IFERROR(_xlfn.XLOOKUP($E40,noverdefornecedor!$A:$A,noverdefornecedor!$B:$B),"")) | K40: =IF($A40="","",IFERROR(_xlfn.XLOOKUP($F40,noverdepacote!$A:$A,noverdepacote!$D:$D),"")) | L40: =IF($A40="","",DATE(YEAR($A40),MONTH($A40),1)) | M40: =IF($A40="","","Noverde") | N40: =IF($A40="","",IFERROR(_xlfn.XLOOKUP($F40,noverdepacote!$A:$A,noverdepacote!$B:$B),""))
J41: =IF($A41="","",IFERROR(_xlfn.XLOOKUP($E41,noverdefornecedor!$A:$A,noverdefornecedor!$B:$B),"")) | K41: =IF($A41="","",IFERROR(_xlfn.XLOOKUP($F41,noverdepacote!$A:$A,noverdepacote!$D:$D),"")) | L41: =IF($A41="","",DATE(YEAR($A41),MONTH($A41),1)) | M41: =IF($A41="","","Noverde") | N41: =IF($A41="","",IFERROR(_xlfn.XLOOKUP($F41,noverdepacote!$A:$A,noverdepacote!$B:$B),""))
J42: =IF($A42="","",IFERROR(_xlfn.XLOOKUP($E42,noverdefornecedor!$A:$A,noverdefornecedor!$B:$B),"")) | K42: =IF($A42="","",IFERROR(_xlfn.XLOOKUP($F42,noverdepacote!$A:$A,noverdepacote!$D:$D),"")) | L42: =IF($A42="","",DATE(YEAR($A42),MONTH($A42),1)) | M42: =IF($A42="","","Noverde") | N42: =IF($A42="","",IFERROR(_xlfn.XLOOKUP($F42,noverdepacote!$A:$A,noverdepacote!$B:$B),""))
J43: =IF($A43="","",IFERROR(_xlfn.XLOOKUP($E43,noverdefornecedor!$A:$A,noverdefornecedor!$B:$B),"")) | K43: =IF($A43="","",IFERROR(_xlfn.XLOOKUP($F43,noverdepacote!$A:$A,noverdepacote!$D:$D),"")) | L43: =IF($A43="","",DATE(YEAR($A43),MONTH($A43),1)) | M43: =IF($A43="","","Noverde") | N43: =IF($A43="","",IFERROR(_xlfn.XLOOKUP($F43,noverdepacote!$A:$A,noverdepacote!$B:$B),""))
J44: =IF($A44="","",IFERROR(_xlfn.XLOOKUP($E44,noverdefornecedor!$A:$A,noverdefornecedor!$B:$B),"")) | K44: =IF($A44="","",IFERROR(_xlfn.XLOOKUP($F44,noverdepacote!$A:$A,noverdepacote!$D:$D),"")) | L44: =IF($A44="","",DATE(YEAR($A44),MONTH($A44),1)) | M44: =IF($A44="","","Noverde") | N44: =IF($A44="","",IFERROR(_xlfn.XLOOKUP($F44,noverdepacote!$A:$A,noverdepacote!$B:$B),""))
J45: =IF($A45="","",IFERROR(_xlfn.XLOOKUP($E45,noverdefornecedor!$A:$A,noverdefornecedor!$B:$B),"")) | K45: =IF($A45="","",IFERROR(_xlfn.XLOOKUP($F45,noverdepacote!$A:$A,noverdepacote!$D:$D),"")) | L45: =IF($A45="","",DATE(YEAR($A45),MONTH($A45),1)) | M45: =IF($A45="","","Noverde") | N45: =IF($A45="","",IFERROR(_xlfn.XLOOKUP($F45,noverdepacote!$A:$A,noverdepacote!$B:$B),""))
J46: =IF($A46="","",IFERROR(_xlfn.XLOOKUP($E46,noverdefornecedor!$A:$A,noverdefornecedor!$B:$B),"")) | K46: =IF($A46="","",IFERROR(_xlfn.XLOOKUP($F46,noverdepacote!$A:$A,noverdepacote!$D:$D),"")) | L46: =IF($A46="","",DATE(YEAR($A46),MONTH($A46),1)) | M46: =IF($A46="","","Noverde") | N46: =IF($A46="","",IFERROR(_xlfn.XLOOKUP($F46,noverdepacote!$A:$A,noverdepacote!$B:$B),""))
J47: =IF($A47="","",IFERROR(_xlfn.XLOOKUP($E47,noverdefornecedor!$A:$A,noverdefornecedor!$B:$B),"")) | K47: =IF($A47="","",IFERROR(_xlfn.XLOOKUP($F47,noverdepacote!$A:$A,noverdepacote!$D:$D),"")) | L47: =IF($A47="","",DATE(YEAR($A47),MONTH($A47),1)) | M47: =IF($A47="","","Noverde") | N47: =IF($A47="","",IFERROR(_xlfn.XLOOKUP($F47,noverdepacote!$A:$A,noverdepacote!$B:$B),""))
J48: =IF($A48="","",IFERROR(_xlfn.XLOOKUP($E48,noverdefornecedor!$A:$A,noverdefornecedor!$B:$B),"")) | K48: =IF($A48="","",IFERROR(_xlfn.XLOOKUP($F48,noverdepacote!$A:$A,noverdepacote!$D:$D),"")) | L48: =IF($A48="","",DATE(YEAR($A48),MONTH($A48),1)) | M48: =IF($A48="","","Noverde") | N48: =IF($A48="","",IFERROR(_xlfn.XLOOKUP($F48,noverdepacote!$A:$A,noverdepacote!$B:$B),""))
... J200: =IF($A200="","",IFERROR(_xlfn.XLOOKUP($E200,noverdefornecedor!$A:$A,noverdefornecedor!$B:$B),"")) | K200: =IF($A200="","",IFERROR(_xlfn.XLOOKUP($F200,noverdepacote!$A:$A,noverdepacote!$D:$D),"")) | L200: =IF($A200="","",DATE(YEAR($A200),MONTH($A200),1)) | M200: =IF($A200="","","Noverde") | N200: =IF($A200="","",IFERROR(_xlfn.XLOOKUP($F200,noverdepacote!$A:$A,noverdepacote!$B:$B),""))

Sheet Dotzprovisões
A1: Data de lançamento | B1: Nº transação | C1: Origem | D1: Nº origem | E1: Ref.3 | F1: Conta de contrapartida | G1: Detalhes | H1: C/D (ML) | I1: Saldo acumulado (MC) | J1: Fornecedor | K1: SubGrupo | L1: Mês/Ano | M1: Empresa | N1: Descrição Conta
C2: SI | I2: 0
A3: 46053 | B3: 15276 | C3: LC | D3: 15276 | E3: F000166 | F3: 3313020 | G3: Provisão Grant Thorton | H3: -34013.61 | I3: -34013.61 | J3: =IF($A3="","",IFERROR(_xlfn.XLOOKUP($E3,dotzfornecedor!$A:$A,dotzfornecedor!$B:$B),"")) -> GRANT THORNTON AUDITORES INDEPENDENTES LTDA | K3: =IF($A3="","",IFERROR(_xlfn.XLOOKUP($F3,dotzpacote!$A:$A,dotzpacote!$D:$D),"")) -> Services | L3: =IF($A3="","",DATE(YEAR($A3),MONTH($A3),1)) -> 46023 | M3: =IF($A3="","","Dotz") -> Dotz | N3: =IF($A3="","",IFERROR(_xlfn.XLOOKUP($F3,dotzpacote!$A:$A,dotzpacote!$B:$B),"")) -> Assessoria Contábil
A4: 46054 | B4: 15573 | C4: LC | D4: 15573 | E4: F000036 | F4: 2111004 | G4: Provisão Pinheiro Guimarães(Estorno) - 15071 | H4: -8449.78 | I4: -42463.39 | J4: =IF($A4="","",IFERROR(_xlfn.XLOOKUP($E4,dotzfornecedor!$A:$A,dotzfornecedor!$B:$B),"")) -> Pinheiro Guimarães | K4: =IF($A4="","",IFERROR(_xlfn.XLOOKUP($F4,dotzpacote!$A:$A,dotzpacote!$D:$D),"")) | L4: =IF($A4="","",DATE(YEAR($A4),MONTH($A4),1)) -> 46054 | M4: =IF($A4="","","Dotz") -> Dotz | N4: =IF($A4="","",IFERROR(_xlfn.XLOOKUP($F4,dotzpacote!$A:$A,dotzpacote!$B:$B),""))
A5: 46081 | B5: 15453 | C5: LC | D5: 15453 | E5: F000166 | F5: 3313020 | G5: Provisão Grant Thorton | H5: -34013.61 | I5: -76477 | J5: =IF($A5="","",IFERROR(_xlfn.XLOOKUP($E5,dotzfornecedor!$A:$A,dotzfornecedor!$B:$B),"")) -> GRANT THORNTON AUDITORES INDEPENDENTES LTDA | K5: =IF($A5="","",IFERROR(_xlfn.XLOOKUP($F5,dotzpacote!$A:$A,dotzpacote!$D:$D),"")) -> Services | L5: =IF($A5="","",DATE(YEAR($A5),MONTH($A5),1)) -> 46054 | M5: =IF($A5="","","Dotz") -> Dotz | N5: =IF($A5="","",IFERROR(_xlfn.XLOOKUP($F5,dotzpacote!$A:$A,dotzpacote!$B:$B),"")) -> Assessoria Contábil
A6: 46112 | B6: 15996 | C6: LC | D6: 15996 | E6: F000166 | F6: 3313020 | G6: Provisão Grant Thorton | H6: -34013.61 | I6: -110490.61 | J6: =IF($A6="","",IFERROR(_xlfn.XLOOKUP($E6,dotzfornecedor!$A:$A,dotzfornecedor!$B:$B),"")) -> GRANT THORNTON AUDITORES INDEPENDENTES LTDA | K6: =IF($A6="","",IFERROR(_xlfn.XLOOKUP($F6,dotzpacote!$A:$A,dotzpacote!$D:$D),"")) -> Services | L6: =IF($A6="","",DATE(YEAR($A6),MONTH($A6),1)) -> 46082 | M6: =IF($A6="","","Dotz") -> Dotz | N6: =IF($A6="","",IFERROR(_xlfn.XLOOKUP($F6,dotzpacote!$A:$A,dotzpacote!$B:$B),"")) -> Assessoria Contábil
A7: 46142 | B7: 16363 | C7: LC | D7: 16363 | E7: F000165 | F7: 3313350 | G7: Provisão nf HeidrickRecrutamento Especializado - F000165 | H7: -61980.91 | I7: -172471.52 | J7: =IF($A7="","",IFERROR(_xlfn.XLOOKUP($E7,dotzfornecedor!$A:$A,dotzfornecedor!$B:$B),"")) -> HEIDRICK & STRUGGLES RECRUTAMENTO ESPECIALIZADO LTDA. | K7: =IF($A7="","",IFERROR(_xlfn.XLOOKUP($F7,dotzpacote!$A:$A,dotzpacote!$D:$D),"")) -> Services | L7: =IF($A7="","",DATE(YEAR($A7),MONTH($A7),1)) -> 46113 | M7: =IF($A7="","","Dotz") -> Dotz | N7: =IF($A7="","",IFERROR(_xlfn.XLOOKUP($F7,dotzpacote!$A:$A,dotzpacote!$B:$B),"")) -> Serviços de Consultoria
A8: 46171 | B8: 16774 | C8: LC | D8: 16774 | E8: F000103 | F8: 3313030 | G8: Provisão NF Mello e Torres - F000103 | H8: -41743.92 | I8: -214215.44 | J8: =IF($A8="","",IFERROR(_xlfn.XLOOKUP($E8,dotzfornecedor!$A:$A,dotzfornecedor!$B:$B),"")) -> Mello e Torres Sociedade de Advogados | K8: =IF($A8="","",IFERROR(_xlfn.XLOOKUP($F8,dotzpacote!$A:$A,dotzpacote!$D:$D),"")) -> Services | L8: =IF($A8="","",DATE(YEAR($A8),MONTH($A8),1)) -> 46143 | M8: =IF($A8="","","Dotz") -> Dotz | N8: =IF($A8="","",IFERROR(_xlfn.XLOOKUP($F8,dotzpacote!$A:$A,dotzpacote!$B:$B),"")) -> Assessoria Jurídica
A9: 46171 | B9: 16775 | C9: LC | D9: 16775 | E9: F000165 | F9: 3313350 | G9: Provisão nf HeidrickRecrutamento Especializado - F000165 | H9: -61980.91 | I9: -276196.35 | J9: =IF($A9="","",IFERROR(_xlfn.XLOOKUP($E9,dotzfornecedor!$A:$A,dotzfornecedor!$B:$B),"")) -> HEIDRICK & STRUGGLES RECRUTAMENTO ESPECIALIZADO LTDA. | K9: =IF($A9="","",IFERROR(_xlfn.XLOOKUP($F9,dotzpacote!$A:$A,dotzpacote!$D:$D),"")) -> Services | L9: =IF($A9="","",DATE(YEAR($A9),MONTH($A9),1)) -> 46143 | M9: =IF($A9="","","Dotz") -> Dotz | N9: =IF($A9="","",IFERROR(_xlfn.XLOOKUP($F9,dotzpacote!$A:$A,dotzpacote!$B:$B),"")) -> Serviços de Consultoria
A10: 46171 | B10: 16809 | C10: LC | D10: 16809 | E10: F000166 | F10: 3313020 | G10: Provisão Grant Thorton | H10: -34013.61 | I10: -310209.96 | J10: =IF($A10="","",IFERROR(_xlfn.XLOOKUP($E10,dotzfornecedor!$A:$A,dotzfornecedor!$B:$B),"")) -> GRANT THORNTON AUDITORES INDEPENDENTES LTDA | K10: =IF($A10="","",IFERROR(_xlfn.XLOOKUP($F10,dotzpacote!$A:$A,dotzpacote!$D:$D),"")) -> Services | L10: =IF($A10="","",DATE(YEAR($A10),MONTH($A10),1)) -> 46143 | M10: =IF($A10="","","Dotz") -> Dotz | N10: =IF($A10="","",IFERROR(_xlfn.XLOOKUP($F10,dotzpacote!$A:$A,dotzpacote!$B:$B),"")) -> Assessoria Contábil
A11: 46171 | B11: 16818 | C11: LC | D11: 16818 | E11: F000023 | F11: 3313350 | G11: Prov. Amortização Action Syst | H11: -9576.28 | I11: -319786.24 | J11: =IF($A11="","",IFERROR(_xlfn.XLOOKUP($E11,dotzfornecedor!$A:$A,dotzfornecedor!$B:$B),"")) -> ACTION SYSTEMS SERVICOS EM INFORMATICA LTDA | K11: =IF($A11="","",IFERROR(_xlfn.XLOOKUP($F11,dotzpacote!$A:$A,dotzpacote!$D:$D),"")) -> Services | L11: =IF($A11="","",DATE(YEAR($A11),MONTH($A11),1)) -> 46143 | M11: =IF($A11="","","Dotz") -> Dotz | N11: =IF($A11="","",IFERROR(_xlfn.XLOOKUP($F11,dotzpacote!$A:$A,dotzpacote!$B:$B),"")) -> Serviços de Consultoria
A12: 46171 | B12: 16819 | C12: LC | D12: 16819 | E12: F000071 | F12: 3313270 | G12: PROV. INVENT SOFTWARE LTDA | H12: -18750 | I12: -338536.24 | J12: =IF($A12="","",IFERROR(_xlfn.XLOOKUP($E12,dotzfornecedor!$A:$A,dotzfornecedor!$B:$B),"")) -> INVENT SOFTWARE LTDA | K12: =IF($A12="","",IFERROR(_xlfn.XLOOKUP($F12,dotzpacote!$A:$A,dotzpacote!$D:$D),"")) -> IT & Telecom | L12: =IF($A12="","",DATE(YEAR($A12),MONTH($A12),1)) -> 46143 | M12: =IF($A12="","","Dotz") -> Dotz | N12: =IF($A12="","",IFERROR(_xlfn.XLOOKUP($F12,dotzpacote!$A:$A,dotzpacote!$B:$B),"")) -> Licenças
A13: 46172 | B13: 16745 | C13: LC | D13: 16745 | E13: F000163 | F13: 3313030 | G13: Provisão MMF e A&M Créditos Previdenciários | H13: -21404.25 | I13: -359940.49 | J13: =IF($A13="","",IFERROR(_xlfn.XLOOKUP($E13,dotzfornecedor!$A:$A,dotzfornecedor!$B:$B),"")) -> MOSS, MUZZI, FALCAO, MASSOTE E WERNECK ADVOGADOS ASSOCIADOS | K13: =IF($A13="","",IFERROR(_xlfn.XLOOKUP($F13,dotzpacote!$A:$A,dotzpacote!$D:$D),"")) -> Services | L13: =IF($A13="","",DATE(YEAR($A13),MONTH($A13),1)) -> 46143 | M13: =IF($A13="","","Dotz") -> Dotz | N13: =IF($A13="","",IFERROR(_xlfn.XLOOKUP($F13,dotzpacote!$A:$A,dotzpacote!$B:$B),"")) -> Assessoria Jurídica
J14: =IF($A14="","",IFERROR(_xlfn.XLOOKUP($E14,dotzfornecedor!$A:$A,dotzfornecedor!$B:$B),"")) | K14: =IF($A14="","",IFERROR(_xlfn.XLOOKUP($F14,dotzpacote!$A:$A,dotzpacote!$D:$D),"")) | L14: =IF($A14="","",DATE(YEAR($A14),MONTH($A14),1)) | M14: =IF($A14="","","Dotz") | N14: =IF($A14="","",IFERROR(_xlfn.XLOOKUP($F14,dotzpacote!$A:$A,dotzpacote!$B:$B),""))
J15: =IF($A15="","",IFERROR(_xlfn.XLOOKUP($E15,dotzfornecedor!$A:$A,dotzfornecedor!$B:$B),"")) | K15: =IF($A15="","",IFERROR(_xlfn.XLOOKUP($F15,dotzpacote!$A:$A,dotzpacote!$D:$D),"")) | L15: =IF($A15="","",DATE(YEAR($A15),MONTH($A15),1)) | M15: =IF($A15="","","Dotz") | N15: =IF($A15="","",IFERROR(_xlfn.XLOOKUP($F15,dotzpacote!$A:$A,dotzpacote!$B:$B),""))
J16: =IF($A16="","",IFERROR(_xlfn.XLOOKUP($E16,dotzfornecedor!$A:$A,dotzfornecedor!$B:$B),"")) | K16: =IF($A16="","",IFERROR(_xlfn.XLOOKUP($F16,dotzpacote!$A:$A,dotzpacote!$D:$D),"")) | L16: =IF($A16="","",DATE(YEAR($A16),MONTH($A16),1)) | M16: =IF($A16="","","Dotz") | N16: =IF($A16="","",IFERROR(_xlfn.XLOOKUP($F16,dotzpacote!$A:$A,dotzpacote!$B:$B),""))
J17: =IF($A17="","",IFERROR(_xlfn.XLOOKUP($E17,dotzfornecedor!$A:$A,dotzfornecedor!$B:$B),"")) | K17: =IF($A17="","",IFERROR(_xlfn.XLOOKUP($F17,dotzpacote!$A:$A,dotzpacote!$D:$D),"")) | L17: =IF($A17="","",DATE(YEAR($A17),MONTH($A17),1)) | M17: =IF($A17="","","Dotz") | N17: =IF($A17="","",IFERROR(_xlfn.XLOOKUP($F17,dotzpacote!$A:$A,dotzpacote!$B:$B),""))
J18: =IF($A18="","",IFERROR(_xlfn.XLOOKUP($E18,dotzfornecedor!$A:$A,dotzfornecedor!$B:$B),"")) | K18: =IF($A18="","",IFERROR(_xlfn.XLOOKUP($F18,dotzpacote!$A:$A,dotzpacote!$D:$D),"")) | L18: =IF($A18="","",DATE(YEAR($A18),MONTH($A18),1)) | M18: =IF($A18="","","Dotz") | N18: =IF($A18="","",IFERROR(_xlfn.XLOOKUP($F18,dotzpacote!$A:$A,dotzpacote!$B:$B),""))
J19: =IF($A19="","",IFERROR(_xlfn.XLOOKUP($E19,dotzfornecedor!$A:$A,dotzfornecedor!$B:$B),"")) | K19: =IF($A19="","",IFERROR(_xlfn.XLOOKUP($F19,dotzpacote!$A:$A,dotzpacote!$D:$D),"")) | L19: =IF($A19="","",DATE(YEAR($A19),MONTH($A19),1)) | M19: =IF($A19="","","Dotz") | N19: =IF($A19="","",IFERROR(_xlfn.XLOOKUP($F19,dotzpacote!$A:$A,dotzpacote!$B:$B),""))
J20: =IF($A20="","",IFERROR(_xlfn.XLOOKUP($E20,dotzfornecedor!$A:$A,dotzfornecedor!$B:$B),"")) | K20: =IF($A20="","",IFERROR(_xlfn.XLOOKUP($F20,dotzpacote!$A:$A,dotzpacote!$D:$D),"")) | L20: =IF($A20="","",DATE(YEAR($A20),MONTH($A20),1)) | M20: =IF($A20="","","Dotz") | N20: =IF($A20="","",IFERROR(_xlfn.XLOOKUP($F20,dotzpacote!$A:$A,dotzpacote!$B:$B),""))
J21: =IF($A21="","",IFERROR(_xlfn.XLOOKUP($E21,dotzfornecedor!$A:$A,dotzfornecedor!$B:$B),"")) | K21: =IF($A21="","",IFERROR(_xlfn.XLOOKUP($F21,dotzpacote!$A:$A,dotzpacote!$D:$D),"")) | L21: =IF($A21="","",DATE(YEAR($A21),MONTH($A21),1)) | M21: =IF($A21="","","Dotz") | N21: =IF($A21="","",IFERROR(_xlfn.XLOOKUP($F21,dotzpacote!$A:$A,dotzpacote!$B:$B),""))
J22: =IF($A22="","",IFERROR(_xlfn.XLOOKUP($E22,dotzfornecedor!$A:$A,dotzfornecedor!$B:$B),"")) | K22: =IF($A22="","",IFERROR(_xlfn.XLOOKUP($F22,dotzpacote!$A:$A,dotzpacote!$D:$D),"")) | L22: =IF($A22="","",DATE(YEAR($A22),MONTH($A22),1)) | M22: =IF($A22="","","Dotz") | N22: =IF($A22="","",IFERROR(_xlfn.XLOOKUP($F22,dotzpacote!$A:$A,dotzpacote!$B:$B),""))
J23: =IF($A23="","",IFERROR(_xlfn.XLOOKUP($E23,dotzfornecedor!$A:$A,dotzfornecedor!$B:$B),"")) | K23: =IF($A23="","",IFERROR(_xlfn.XLOOKUP($F23,dotzpacote!$A:$A,dotzpacote!$D:$D),"")) | L23: =IF($A23="","",DATE(YEAR($A23),MONTH($A23),1)) | M23: =IF($A23="","","Dotz") | N23: =IF($A23="","",IFERROR(_xlfn.XLOOKUP($F23,dotzpacote!$A:$A,dotzpacote!$B:$B),""))
J24: =IF($A24="","",IFERROR(_xlfn.XLOOKUP($E24,dotzfornecedor!$A:$A,dotzfornecedor!$B:$B),"")) | K24: =IF($A24="","",IFERROR(_xlfn.XLOOKUP($F24,dotzpacote!$A:$A,dotzpacote!$D:$D),"")) | L24: =IF($A24="","",DATE(YEAR($A24),MONTH($A24),1)) | M24: =IF($A24="","","Dotz") | N24: =IF($A24="","",IFERROR(_xlfn.XLOOKUP($F24,dotzpacote!$A:$A,dotzpacote!$B:$B),""))
J25: =IF($A25="","",IFERROR(_xlfn.XLOOKUP($E25,dotzfornecedor!$A:$A,dotzfornecedor!$B:$B),"")) | K25: =IF($A25="","",IFERROR(_xlfn.XLOOKUP($F25,dotzpacote!$A:$A,dotzpacote!$D:$D),"")) | L25: =IF($A25="","",DATE(YEAR($A25),MONTH($A25),1)) | M25: =IF($A25="","","Dotz") | N25: =IF($A25="","",IFERROR(_xlfn.XLOOKUP($F25,dotzpacote!$A:$A,dotzpacote!$B:$B),""))
... J200: =IF($A200="","",IFERROR(_xlfn.XLOOKUP($E200,dotzfornecedor!$A:$A,dotzfornecedor!$B:$B),"")) | K200: =IF($A200="","",IFERROR(_xlfn.XLOOKUP($F200,dotzpacote!$A:$A,dotzpacote!$D:$D),"")) | L200: =IF($A200="","",DATE(YEAR($A200),MONTH($A200),1)) | M200: =IF($A200="","","Dotz") | N200: =IF($A200="","",IFERROR(_xlfn.XLOOKUP($F200,dotzpacote!$A:$A,dotzpacote!$B:$B),""))

Sheet PAYprovisões
A1: Data de lançamento | B1: Nº transação | C1: Origem | D1: Nº origem | E1: Ref.3 | F1: Conta de contrapartida | G1: Detalhes | H1: C/D (ML) | I1: Saldo acumulado (MC) | J1: Fornecedor | K1: SubGrupo | L1: Mês/Ano | M1: Empresa | N1: Descrição Conta
C2: SI | I2: 0
A3: 46080 | B3: 43065 | C3: LC | D3: 43065 | E3: F000119 | F3: 81763005002 | G3: Provisão Grant Thorton | H3: -5833.33 | I3: -5833.33 | J3: =IF($A3="","",IFERROR(_xlfn.XLOOKUP($E3,payfornecedor!$A:$A,payfornecedor!$B:$B),"")) -> GRANT THORNTON AUDITORES INDEPENDENTES LTDA | K3: =IF($A3="","",IFERROR(_xlfn.XLOOKUP($F3,paypacote!$A:$A,paypacote!$D:$D),"")) -> Services | L3: =IF($A3="","",DATE(YEAR($A3),MONTH($A3),1)) -> 46054 | M3: =IF($A3="","","PAY") -> PAY | N3: =IF($A3="","",IFERROR(_xlfn.XLOOKUP($F3,paypacote!$A:$A,paypacote!$B:$B),"")) -> Assessoria Contábil e Auditoria
A4: 46112 | B4: 43819 | C4: LC | D4: 43819 | E4: F000119 | F4: 81763005002 | G4: Provisão Grant Thorton | H4: -5833.33 | I4: -11666.66 | J4: =IF($A4="","",IFERROR(_xlfn.XLOOKUP($E4,payfornecedor!$A:$A,payfornecedor!$B:$B),"")) -> GRANT THORNTON AUDITORES INDEPENDENTES LTDA | K4: =IF($A4="","",IFERROR(_xlfn.XLOOKUP($F4,paypacote!$A:$A,paypacote!$D:$D),"")) -> Services | L4: =IF($A4="","",DATE(YEAR($A4),MONTH($A4),1)) -> 46082 | M4: =IF($A4="","","PAY") -> PAY | N4: =IF($A4="","",IFERROR(_xlfn.XLOOKUP($F4,paypacote!$A:$A,paypacote!$B:$B),"")) -> Assessoria Contábil e Auditoria
A5: 46113 | B5: 44280 | C5: LC | D5: 44280 | E5: F000119 | F5: 81763005002 | G5: Provisão Grant Thorton | H5: -5833.33 | I5: -17499.99 | J5: =IF($A5="","",IFERROR(_xlfn.XLOOKUP($E5,payfornecedor!$A:$A,payfornecedor!$B:$B),"")) -> GRANT THORNTON AUDITORES INDEPENDENTES LTDA | K5: =IF($A5="","",IFERROR(_xlfn.XLOOKUP($F5,paypacote!$A:$A,paypacote!$D:$D),"")) -> Services | L5: =IF($A5="","",DATE(YEAR($A5),MONTH($A5),1)) -> 46113 | M5: =IF($A5="","","PAY") -> PAY | N5: =IF($A5="","",IFERROR(_xlfn.XLOOKUP($F5,paypacote!$A:$A,paypacote!$B:$B),"")) -> Assessoria Contábil e Auditoria
A6: 46171 | B6: 44823 | C6: LC | D6: 44823 | E6: F000072 | F6: 81739008007 | G6: Provisão NF TPZ soluções - F000072 | H6: -57307 | I6: -74806.99 | J6: =IF($A6="","",IFERROR(_xlfn.XLOOKUP($E6,payfornecedor!$A:$A,payfornecedor!$B:$B),"")) -> TPZ SOLUCOES DIGITAIS LTDA. | K6: =IF($A6="","",IFERROR(_xlfn.XLOOKUP($F6,paypacote!$A:$A,paypacote!$D:$D),"")) -> Other costs - Dotz Pay | L6: =IF($A6="","",DATE(YEAR($A6),MONTH($A6),1)) -> 46143 | M6: =IF($A6="","","PAY") -> PAY | N6: =IF($A6="","",IFERROR(_xlfn.XLOOKUP($F6,paypacote!$A:$A,paypacote!$B:$B),"")) -> Onboarding
J7: =IF($A7="","",IFERROR(_xlfn.XLOOKUP($E7,payfornecedor!$A:$A,payfornecedor!$B:$B),"")) | K7: =IF($A7="","",IFERROR(_xlfn.XLOOKUP($F7,paypacote!$A:$A,paypacote!$D:$D),"")) | L7: =IF($A7="","",DATE(YEAR($A7),MONTH($A7),1)) | M7: =IF($A7="","","PAY") | N7: =IF($A7="","",IFERROR(_xlfn.XLOOKUP($F7,paypacote!$A:$A,paypacote!$B:$B),""))
J8: =IF($A8="","",IFERROR(_xlfn.XLOOKUP($E8,payfornecedor!$A:$A,payfornecedor!$B:$B),"")) | K8: =IF($A8="","",IFERROR(_xlfn.XLOOKUP($F8,paypacote!$A:$A,paypacote!$D:$D),"")) | L8: =IF($A8="","",DATE(YEAR($A8),MONTH($A8),1)) | M8: =IF($A8="","","PAY") | N8: =IF($A8="","",IFERROR(_xlfn.XLOOKUP($F8,paypacote!$A:$A,paypacote!$B:$B),""))
J9: =IF($A9="","",IFERROR(_xlfn.XLOOKUP($E9,payfornecedor!$A:$A,payfornecedor!$B:$B),"")) | K9: =IF($A9="","",IFERROR(_xlfn.XLOOKUP($F9,paypacote!$A:$A,paypacote!$D:$D),"")) | L9: =IF($A9="","",DATE(YEAR($A9),MONTH($A9),1)) | M9: =IF($A9="","","PAY") | N9: =IF($A9="","",IFERROR(_xlfn.XLOOKUP($F9,paypacote!$A:$A,paypacote!$B:$B),""))
J10: =IF($A10="","",IFERROR(_xlfn.XLOOKUP($E10,payfornecedor!$A:$A,payfornecedor!$B:$B),"")) | K10: =IF($A10="","",IFERROR(_xlfn.XLOOKUP($F10,paypacote!$A:$A,paypacote!$D:$D),"")) | L10: =IF($A10="","",DATE(YEAR($A10),MONTH($A10),1)) | M10: =IF($A10="","","PAY") | N10: =IF($A10="","",IFERROR(_xlfn.XLOOKUP($F10,paypacote!$A:$A,paypacote!$B:$B),""))
J11: =IF($A11="","",IFERROR(_xlfn.XLOOKUP($E11,payfornecedor!$A:$A,payfornecedor!$B:$B),"")) | K11: =IF($A11="","",IFERROR(_xlfn.XLOOKUP($F11,paypacote!$A:$A,paypacote!$D:$D),"")) | L11: =IF($A11="","",DATE(YEAR($A11),MONTH($A11),1)) | M11: =IF($A11="","","PAY") | N11: =IF($A11="","",IFERROR(_xlfn.XLOOKUP($F11,paypacote!$A:$A,paypacote!$B:$B),""))
J12: =IF($A12="","",IFERROR(_xlfn.XLOOKUP($E12,payfornecedor!$A:$A,payfornecedor!$B:$B),"")) | K12: =IF($A12="","",IFERROR(_xlfn.XLOOKUP($F12,paypacote!$A:$A,paypacote!$D:$D),"")) | L12: =IF($A12="","",DATE(YEAR($A12),MONTH($A12),1)) | M12: =IF($A12="","","PAY") | N12: =IF($A12="","",IFERROR(_xlfn.XLOOKUP($F12,paypacote!$A:$A,paypacote!$B:$B),""))
J13: =IF($A13="","",IFERROR(_xlfn.XLOOKUP($E13,payfornecedor!$A:$A,payfornecedor!$B:$B),"")) | K13: =IF($A13="","",IFERROR(_xlfn.XLOOKUP($F13,paypacote!$A:$A,paypacote!$D:$D),"")) | L13: =IF($A13="","",DATE(YEAR($A13),MONTH($A13),1)) | M13: =IF($A13="","","PAY") | N13: =IF($A13="","",IFERROR(_xlfn.XLOOKUP($F13,paypacote!$A:$A,paypacote!$B:$B),""))
J14: =IF($A14="","",IFERROR(_xlfn.XLOOKUP($E14,payfornecedor!$A:$A,payfornecedor!$B:$B),"")) | K14: =IF($A14="","",IFERROR(_xlfn.XLOOKUP($F14,paypacote!$A:$A,paypacote!$D:$D),"")) | L14: =IF($A14="","",DATE(YEAR($A14),MONTH($A14),1)) | M14: =IF($A14="","","PAY") | N14: =IF($A14="","",IFERROR(_xlfn.XLOOKUP($F14,paypacote!$A:$A,paypacote!$B:$B),""))
J15: =IF($A15="","",IFERROR(_xlfn.XLOOKUP($E15,payfornecedor!$A:$A,payfornecedor!$B:$B),"")) | K15: =IF($A15="","",IFERROR(_xlfn.XLOOKUP($F15,paypacote!$A:$A,paypacote!$D:$D),"")) | L15: =IF($A15="","",DATE(YEAR($A15),MONTH($A15),1)) | M15: =IF($A15="","","PAY") | N15: =IF($A15="","",IFERROR(_xlfn.XLOOKUP($F15,paypacote!$A:$A,paypacote!$B:$B),""))
J16: =IF($A16="","",IFERROR(_xlfn.XLOOKUP($E16,payfornecedor!$A:$A,payfornecedor!$B:$B),"")) | K16: =IF($A16="","",IFERROR(_xlfn.XLOOKUP($F16,paypacote!$A:$A,paypacote!$D:$D),"")) | L16: =IF($A16="","",DATE(YEAR($A16),MONTH($A16),1)) | M16: =IF($A16="","","PAY") | N16: =IF($A16="","",IFERROR(_xlfn.XLOOKUP($F16,paypacote!$A:$A,paypacote!$B:$B),""))
J17: =IF($A17="","",IFERROR(_xlfn.XLOOKUP($E17,payfornecedor!$A:$A,payfornecedor!$B:$B),"")) | K17: =IF($A17="","",IFERROR(_xlfn.XLOOKUP($F17,paypacote!$A:$A,paypacote!$D:$D),"")) | L17: =IF($A17="","",DATE(YEAR($A17),MONTH($A17),1)) | M17: =IF($A17="","","PAY") | N17: =IF($A17="","",IFERROR(_xlfn.XLOOKUP($F17,paypacote!$A:$A,paypacote!$B:$B),""))
J18: =IF($A18="","",IFERROR(_xlfn.XLOOKUP($E18,payfornecedor!$A:$A,payfornecedor!$B:$B),"")) | K18: =IF($A18="","",IFERROR(_xlfn.XLOOKUP($F18,paypacote!$A:$A,paypacote!$D:$D),"")) | L18: =IF($A18="","",DATE(YEAR($A18),MONTH($A18),1)) | M18: =IF($A18="","","PAY") | N18: =IF($A18="","",IFERROR(_xlfn.XLOOKUP($F18,paypacote!$A:$A,paypacote!$B:$B),""))
... J200: =IF($A200="","",IFERROR(_xlfn.XLOOKUP($E200,payfornecedor!$A:$A,payfornecedor!$B:$B),"")) | K200: =IF($A200="","",IFERROR(_xlfn.XLOOKUP($F200,paypacote!$A:$A,paypacote!$D:$D),"")) | L200: =IF($A200="","",DATE(YEAR($A200),MONTH($A200),1)) | M200: =IF($A200="","","PAY") | N200: =IF($A200="","",IFERROR(_xlfn.XLOOKUP($F200,paypacote!$A:$A,paypacote!$B:$B),""))

Sheet cbsmpacote
A1: Conta | B1: Descrção | C1: Grupo | D1: SubGrupo
B2: Net Revenues
B3: Gross Revenues
B4: Spread
A5: 3111152 | B5: Receita de Venda de Dotz - Clube Dotz | C5: Gross Revenues | D5: Spread
A6: 3111150 | B6: Receita de Venda de Dotz - Non Split Fee | C6: Gross Revenues | D6: Spread
A7: 3111154 | B7: Receita de Venda de Dotz - Pré-Pago | C7: Gross Revenues | D7: Spread
B8: TOTAL DE AJUSTES
B9: Redemption
A10: 3111171 | B10: Receita de Resgate de Dotz - Completa Dotz | C10: Gross Revenues | D10: Redemption
A11: 3111174 | B11: Receita de Resgate de Dotz - Pré-Pago | C11: Gross Revenues | D11: Redemption
A12: 3111172 | B12: Receita de Resgate de Dotz - Clube Dotz | C12: Gross Revenues | D12: Redemption
A13: 3111170 | B13: Receita de Resgate de Dotz - Non Split Fee | C13: Gross Revenues | D13: Redemption
A14: 3111160 | B14: Receita de Resgate de Dotz - Split Fee e Projetos Especiais | C14: Gross Revenues | D14: Redemption
A15: 3111199 | B15: Receita de Resgate de Dotz a Faturar | C15: Gross Revenues | D15: Redemption
A16: 3111173 | B16: Receita de Resgate de Dotz - Viaja | C16: Gross Revenues | D16: Redemption
B17: TOTAL DE AJUSTES
B18: Breakage
A19: 3111451 | B19: Receita de Expiração de Dotz - Completa Dotz | C19: Gross Revenues | D19: Breakage
A20: 3113100 | B20: Projeto Franquia - Receita de Venda de Dotz - Non Split Fee | C20: Gross Revenues | D20: Breakage
A21: 3111450 | B21: Receita de Expiração de Dotz - Non Split Fee | C21: Gross Revenues | D21: Breakage
A22: 3113101 | B22: Projeto Franquia - Receita de Expiração de Dotz - Non Split Fee | C22: Gross Revenues | D22: Breakage
A23: 3111452 | B23: Receita de Expiração de Dotz - Clube Dotz | C23: Gross Revenues | D23: Breakage
A24: 3111454 | B24: Receita de Expiração de Dotz - Pré-Pago | C24: Gross Revenues | D24: Breakage
B25: TOTAL DE AJUSTES
B26: Service Revenues
B27: Fee
A28: 3111300 | B28: Receita Serviços de Marketing | C28: Service Revenues | D28: Fee
A29: 3111200 | B29: Receita Serviços - Comissão | C29: Service Revenues | D29: Fee
B30: TOTAL DE AJUSTES
B31: Service Revenues - Dotz Pay
B32: TOTAL DE AJUSTES
B33: Service Revenues - Noverde
B34: TOTAL DE AJUSTES
B35: (-) Sales Tax & Deductions
B36: Pis
A37: 3131200 | B37: Pis - Serviços Prestados | C37: (-) Sales Tax & Deductions | D37: Sales Tax
A38: 3131110 | B38: Pis - Vendas | C38: (-) Sales Tax & Deductions | D38: Sales Tax
B39: TOTAL DE AJUSTES
B40: Cofins
A41: 3131210 | B41: Cofins - Serviços Prestados | C41: (-) Sales Tax & Deductions | D41: Sales Tax
A42: 3131120 | B42: Cofins - Vendas | C42: (-) Sales Tax & Deductions | D42: Sales Tax
B43: TOTAL DE AJUSTES
B44: ISS
A45: 3131130 | B45: Iss | C45: (-) Sales Tax & Deductions | D45: Sales Tax
B46: TOTAL DE AJUSTES
B47: Deductions
A48: 3312060 | B48: (-)Pis Crédito Insumos | C48: (-) Sales Tax & Deductions | D48: Deductions
A49: 3312070 | B49: (-)Cofins Crédito Insumos | C49: (-) Sales Tax & Deductions | D49: Deductions
A50: 3211004 | B50: (-) Cofins s/ Troca Dotz | C50: (-) Sales Tax & Deductions | D50: Deductions
A51: 3211005 | B51: (-) Pis s/ Troca Dotz | C51: (-) Sales Tax & Deductions | D51: Deductions
A52: 3121100 | B52: Vendas Canceladas | C52: (-) Sales Tax & Deductions | D52: Deductions
B53: TOTAL DE AJUSTES
B54: (-) Costs
B55: Redemption Cost
A56: 3211006 | B56: Arredondamento | C56: (-) Costs | D56: Redemption Cost
A57: 3211003 | B57: Custo de Troca Dotz | C57: (-) Costs | D57: Redemption Cost
A58: 3211010 | B58: (-) Custo de Troca Promodotz | C58: (-) Costs | D58: Redemption Cost
B59: TOTAL DE AJUSTES
B60: Coop Media
B61: TOTAL DE AJUSTES
B62: BV & EAN
A63: 3211008 | B63: Resultado com Bonificação de Venda - BV Faturamento | C63: (-) Costs | D63: BV & EAN
A64: 3211011 | B64: Resultado com Bonificação de Venda - BV Abatimento | C64: (-) Costs | D64: BV & EAN
B65: TOTAL DE AJUSTES
B66: (-) Operational Costs
B67: Other costs - CBSM CAT
A68: 3211007 | B68: CAT - Publicidade e Mídia | C68: (-) Operational Costs | D68: Other costs - CBSM CAT
A69: 3211023 | B69: CAT - Outras Despesas | C69: (-) Operational Costs | D69: Other costs - CBSM CAT
A70: 3211021 | B70: CAT - Promodotz | C70: (-) Operational Costs | D70: Other costs - CBSM CAT
A71: 3211020 | B71: CAT - Gastos com tecnologia | C71: (-) Operational Costs | D71: Other costs - CBSM CAT
A72: 3211024 | B72: CAT - Promodotz Novo Modelo | C72: (-) Operational Costs | D72: Other costs - CBSM CAT
B73: TOTAL DE AJUSTES
B74: Other costs - Dotz Pay
B75: TOTAL DE AJUSTES
B76: Other costs - NoVerde
B77: TOTAL DE AJUSTES
B78: Gross Profit
B79: %
B80: TOTAL DE AJUSTES
B81: SG&A
B82: Personnel
A83: 3313200 | B83: Estacionamento | C83: SG&A | D83: Personnel
A84: 3313370 | B84: Serviços Prestados PJ | C84: SG&A | D84: PersonnelNF
A85: 3313110 | B85: Combustível | C85: SG&A | D85: Personnel
A86: 3313121 | B86: Refeição | C86: SG&A | D86: PersonnelNF
A87: 3311170 | B87: Vale Refeição | C87: SG&A | D87: PersonnelNF
A88: 3311180 | B88: Vale Transporte | C88: SG&A | D88: PersonnelNF
A89: 3311110 | B89: Gratificações | C89: SG&A | D89: Personnel
A90: 3311120 | B90: Seguro de Vida | C90: SG&A | D90: PersonnelNF
A91: 3311130 | B91: Assistência Médica | C91: SG&A | D91: PersonnelNF
A92: 3311260 | B92: Multas e Indenizações Trabalhistas | C92: SG&A | D92: Personnel
A93: 3311270 | B93: Verbas Rescisórias | C93: SG&A | D93: Personnel
A94: 3311200 | B94: Exames | C94: SG&A | D94: PersonnelNF
... A109: 3311060 | B109: Comissão de Vendas | C109: SG&A | D109: Personnel
B110: TOTAL DE AJUSTES
B111: Bonus
A112: 3311160 | B112: Provisão Remuneração Variável | C112: SG&A | D112: Bonus
A113: 3311162 | B113: PLR | C113: SG&A | D113: Bonus
B114: TOTAL DE AJUSTES
...

Sheet dotzpacote
A1: Conta | B1: Descrção | C1: Grupo | D1: SubGrupo
B2: Net Revenues
B3: Gross Revenues
B4: Spread
B5: TOTAL DE AJUSTES
B6: Redemption
B7: TOTAL DE AJUSTES
B8: Breakage
B9: TOTAL DE AJUSTES
B10: Service Revenues
B11: Fee
B12: TOTAL DE AJUSTES
B13: Service Revenues - Dotz Pay
... B18: Pis
A19: 3131110 | B19: Pis - Vendas | C19: (-) Sales Tax & Deductions | D19: Sales Tax
B20: TOTAL DE AJUSTES
B21: Cofins
A22: 3131120 | B22: Cofins - Vendas | C22: (-) Sales Tax & Deductions | D22: Sales Tax
B23: TOTAL DE AJUSTES
B24: ISS
B25: TOTAL DE AJUSTES
B26: Deductions
B27: TOTAL DE AJUSTES
B28: (-) Costs
B29: Redemption Cost
B30: TOTAL DE AJUSTES
B31: Coop Media
B32: TOTAL DE AJUSTES
B33: BV & EAN
B34: TOTAL DE AJUSTES
... B46: Personnel
A47: 3311170 | B47: Vale Refeição | C47: SG&A | D47: Personnel
A48: 3311110 | B48: Gratificações | C48: SG&A | D48: Personnel
A49: 3311130 | B49: Assistência Médica | C49: SG&A | D49: PersonnelNF
A50: 3313200 | B50: Estacionamento | C50: SG&A | D50: PersonnelNF
A51: 3311001 | B51: Cost Sharing | C51: SG&A | D51: Personnel
A52: 3311270 | B52: Multas e Indenizações | C52: SG&A | D52: Personnel
A53: 3311220 | B53: Outros Benefícios | C53: SG&A | D53: PersonnelNF
A54: 3311070 | B54: Férias | C54: SG&A | D54: Personnel
A55: 3311080 | B55: Triênio | C55: SG&A | D55: Personnel
A56: 3311010 | B56: Pró-Labore | C56: SG&A | D56: Personnel
A57: 3311090 | B57: Estagiários | C57: SG&A | D57: PersonnelNF
A58: 3311100 | B58: 13 Salário | C58: SG&A | D58: Personnel
... A62: 3311131 | B62: Assistência Odontológica | C62: SG&A | D62: PersonnelNF
B63: TOTAL DE AJUSTES
B64: Bonus
A65: 3311160 | B65: Provisão Remuneração Variável | C65: SG&A | D65: Bonus
A66: 3311162 | B66: PLR | C66: SG&A | D66: Bonus
B67: TOTAL DE AJUSTES
B68: Recruitment & Development People
A69: 3311240 | B69: Endomarketing | C69: SG&A | D69: Recruitment & Development People
B70: TOTAL DE AJUSTES
B71: Facilities & Rentals
A72: 3313280 | B72: Limpeza e Conservação | C72: SG&A | D72: Facilities & Rentals
A73: 3313300 | B73: Locação de Veículos | C73: SG&A | D73: Facilities & Rentals
A74: 3313310 | B74: Manutenção e Reparos | C74: SG&A | D74: Facilities & Rentals
A75: 3312010 | B75: Aluguéis e Condomínios | C75: SG&A | D75: Facilities & Rentals
A76: 3313140 | B76: Copa e Cozinha | C76: SG&A | D76: Facilities & Rentals
A77: 3313320 | B77: Material de Escritório e Informática | C77: SG&A | D77: Facilities & Rentals
A78: 3312020 | B78: Energia Elétrica | C78: SG&A | D78: Facilities & Rentals
A79: 3312050 | B79: Condomínios | C79: SG&A | D79: Facilities & Rentals
A80: 3312030 | B80: Iptu | C80: SG&A | D80: Facilities & Rentals
A81: 3313290 | B81: Locação de Máquinas e Equipamentos | C81: SG&A | D81: Facilities & Rentals
B82: TOTAL DE AJUSTES
B83: Services | D83: Services
A84: 3313220 | B84: Gráfica e Impressões | C84: SG&A | D84: Services
A85: 3313030 | B85: Assessoria Jurídica | C85: SG&A | D85: Services
A86: 3611007 | B86: Despesas Indedutíveis | C86: SG&A | D86: Services
A87: 3313050 | B87: Associação de Classes | C87: SG&A | D87: Services
A88: 3314030 | B88: Taxas Municipais, Estaduais e Federais | C88: SG&A | D88: Services
A89: 3313070 | B89: Cartório | C89: SG&A | D89: Services
A90: 3313020 | B90: Assessoria Contábil | C90: SG&A | D90: Services
A91: 3313350 | B91: Serviços de Consultoria | C91: SG&A | D91: Services
A92: 3313340 | B92: Seguros | C92: SG&A | D92: Services
B93: TOTAL DE AJUSTES
B94: CRM & Call Center
B95: TOTAL DE AJUSTES
B96: Growth Marketing
A97: 3316090 | B97: Outras Despesas | C97: SG&A | D97: Growth Marketing
A98: 3316110 | B98: Consultoria de MKT | C98: SG&A | D98: Growth Marketing
B99: TOTAL DE AJUSTES
B100: Commercial
A101: 3313210 | B101: Eventos | C101: SG&A | D101: Commercial
A102: 3313260 | B102: Kilometragem | C102: SG&A | D102: Commercial
B103: TOTAL DE AJUSTES
B104: IT & Telecom
A105: 3313270 | B105: Licenças | C105: SG&A | D105: IT & Telecom
A106: 3313230 | B106: Hosting, Links E Pos | C106: SG&A | D106: IT & Telecom
A107: 3313240 | B107: Internet | C107: SG&A | D107: IT & Telecom
A108: 3313380 | B108: Suporte Técnico | C108: SG&A | D108: IT & Telecom
B109: TOTAL DE AJUSTES
B110: Travel
A111: 3313420 | B111: Viagens - Passagem | C111: SG&A | D111: Travel
A112: 3313430 | B112: Viagens - Refeições | C112: SG&A | D112: Travel
A113: 3313120 | B113: Condução | C113: SG&A | D113: Travel
A114: 3313400 | B114: Viagens - Estadia | C114: SG&A | D114: Travel
B115: TOTAL DE AJUSTES
B116: Financial Losses over Cyber attacks
A117: 3313480 | B117: Indenizações | C117: SG&A | D117: Financial Losses over Cyber attacks
B118: TOTAL DE AJUSTES
...

Sheet noverdepacote
A1: Conta | B1: Descrção | C1: Grupo | D1: SubGrupo
B2: Net Revenues
B3: Gross Revenues
B4: Spread
B5: TOTAL DE AJUSTES
B6: Redemption
B7: TOTAL DE AJUSTES
B8: Breakage
B9: TOTAL DE AJUSTES
B10: Service Revenues
B11: Fee
B12: TOTAL DE AJUSTES
B13: Service Revenues - Dotz Pay
... B15: Service Revenues - Noverde
A16: 71510000003 | B16: Outras Receitas Financeiras | C16: Gross Revenues | D16: Service Revenues - Noverde
A17: 71999009004 | B17: Fee de Performance | C17: Gross Revenues | D17: Service Revenues - Noverde
A18: 71999009007 | B18: Receita EP | C18: Gross Revenues | D18: Service Revenues - Noverde
A19: 71999009002 | B19: Provisao Servicos Prestados - Mercado Interno | C19: Gross Revenues | D19: Service Revenues - Noverde
A20: 71999009012 | B20: Receita Seguro Prestamista | C20: Gross Revenues | D20: Service Revenues - Noverde
A21: 71999009010 | B21: Receita de Cobrança | C21: Gross Revenues | D21: Service Revenues - Noverde
A22: 71999009008 | B22: Receita FGTS | C22: Gross Revenues | D22: Service Revenues - Noverde
A23: 71999009011 | B23: Outras Receitas NoVerde | C23: Gross Revenues | D23: Service Revenues - Noverde
A24: 71999009009 | B24: Receita BNPL | C24: Gross Revenues | D24: Service Revenues - Noverde
A25: 71999009014 | B25: Provisão Receita Seguro Prestamista | C25: Gross Revenues | D25: Service Revenues - Noverde
A26: 71999009016 | B26: Receita de Risk As A Service | C26: Gross Revenues | D26: Service Revenues - Noverde
A27: 71999009017 | B27: Receita de Referral | C27: Gross Revenues | D27: Service Revenues - Noverde
B28: TOTAL DE AJUSTES
B29: (-) Sales Tax & Deductions
B30: Pis
A31: 81933000003 | B31: Pis - Serviços Prestados | C31: (-) Sales Tax & Deductions | D31: Sales Tax
B32: TOTAL DE AJUSTES
B33: Cofins
A34: 81930003003 | B34: Cofins - Serviços Prestados | C34: (-) Sales Tax & Deductions | D34: Sales Tax
B35: TOTAL DE AJUSTES
B36: ISS
A37: 81925001001 | B37: (-) ISS sobre Vendas | C37: (-) Sales Tax & Deductions | D37: Sales Tax
B38: TOTAL DE AJUSTES
B39: Deductions
A40: 81706000002 | B40: (-)Cofins Crédito sobre insumos | C40: (-) Sales Tax & Deductions | D40: Deductions
A41: 81703003002 | B41: (-)Pis Crédito sobre insumos | C41: (-) Sales Tax & Deductions | D41: Deductions
B42: TOTAL DE AJUSTES
B43: (-) Costs
B44: Redemption Cost
B45: TOTAL DE AJUSTES
B46: Coop Media
B47: TOTAL DE AJUSTES
B48: BV & EAN
B49: TOTAL DE AJUSTES
B50: (-) Operational Costs
B51: Other costs - CBSM CAT
B52: TOTAL DE AJUSTES
B53: Other costs - Dotz Pay
... B55: Other costs - NoVerde
A56: 81757104023 | B56: Licenças (Custo) | C56: (-) Operational Costs | D56: Other costs - NoVerde
A57: 81757104006 | B57: Hosting e Links (Custo) | C57: (-) Operational Costs | D57: Other costs - NoVerde
A58: 81739008004 | B58: Promo Dotz Acquisition | C58: (-) Operational Costs | D58: Other costs - NoVerde
A59: 81763005007 | B59: Custo De Prevenção de Fraudes | C59: (-) Operational Costs | D59: Other costs - NoVerde
A60: 81745009011 | B60: Custo de Marketing (Custo) | C60: (-) Operational Costs | D60: Other costs - NoVerde
A61: 81763005004 | B61: Suporte Técnico (Custo) | C61: (-) Operational Costs | D61: Other costs - NoVerde
A62: 81763005006 | B62: Custos de Credito | C62: (-) Operational Costs | D62: Other costs - NoVerde
A63: 81763005005 | B63: Custo de Cobrança (Custo) | C63: (-) Operational Costs | D63: Other costs - NoVerde
A64: 81757104032 | B64: Custo de Comunicação (Custo) | C64: (-) Operational Costs | D64: Other costs - NoVerde
B65: TOTAL DE AJUSTES
B66: Gross Profit
B67: %
B68: TOTAL DE AJUSTES
B69: SG&A
B70: Personnel
A71: 81727003005 | B71: D.S.R. | C71: SG&A | D71: Personnel
A72: 81727003014 | B72: Multas e Indenizações Trabalhistas | C72: SG&A | D72: Personnel
A73: 81757004001 | B73: Serviços Prestados - PJ (Despesa) | C73: SG&A | D73: PersonnelNF
A74: 81727003020 | B74: Exames | C74: SG&A | D74: PersonnelNF
A75: 81727003015 | B75: Verbas Rescisórias | C75: SG&A | D75: Personnel
A76: 81733004012 | B76: Provisao Fgts S/13.Salario | C76: SG&A | D76: Personnel
A77: 81733004011 | B77: Provisao Inss S/13.Salario | C77: SG&A | D77: Personnel
A78: 81733004014 | B78: Provisao Fgts S/Ferias | C78: SG&A | D78: Personnel
A79: 81733004002 | B79: Salários | C79: SG&A | D79: Personnel
A80: 81730502001 | B80: Inss | C80: SG&A | D80: Personnel
A81: 81727003011 | B81: Recrutamento | C81: SG&A | D81: PersonnelNF
A82: 81733004013 | B82: Provisao Inss S/Ferias | C82: SG&A | D82: Personnel
... A100: 81733004099 | B100: Cost Shering | C100: SG&A | D100: Personnel
B101: TOTAL DE AJUSTES
B102: Bonus
A103: 81733004007 | B103: Provisão Remuneração Variável | C103: SG&A | D103: Bonus
A104: 81733004008 | B104: Remuneração Variável | C104: SG&A | D104: Bonus
A105: 81733004009 | B105: PLR | C105: SG&A | D105: Bonus
B106: TOTAL DE AJUSTES
B107: Recruitment & Development People
A108: 81727003012 | B108: Endomarketing | C108: SG&A | D108: Recruitment & Development People
B109: TOTAL DE AJUSTES
B110: Facilities & Rentals
A111: 81757104008 | B111: Aluguéis (coworking e arquivo) | C111: SG&A | D111: Facilities & Rentals
A112: 81799000005 | B112: Condomínios | C112: SG&A | D112: Facilities & Rentals
A113: 81757104003 | B113: Correios | C113: SG&A | D113: Facilities & Rentals
A114: 81706000001 | B114: Aluguéis - Operacional | C114: SG&A | D114: Facilities & Rentals
A115: 81724006002 | B115: Material de Escritório e Informática | C115: SG&A | D115: Facilities & Rentals
B116: TOTAL DE AJUSTES
B117: Services
A118: 81745009019 | B118: Serviços de Marketing (Despesa) | C118: SG&A | D118: Growth Marketing
A119: 81757104016 | B119: Copa e Cozinha | C119: SG&A | D119: Services
...

Sheet paypacote
A1: Conta | B1: Descrção | C1: Grupo | D1: SubGrupo
B2: Net Revenues
B3: Gross Revenues
B4: Spread
B5: TOTAL DE AJUSTES
B6: Redemption
B7: TOTAL DE AJUSTES
B8: Breakage
B9: TOTAL DE AJUSTES
B10: Service Revenues
B11: Fee
B12: TOTAL DE AJUSTES
B13: Service Revenues - Dotz Pay
A14: 71795210001 | B14: Tarifa 2a via de cartão | C14: Gross Revenues | D14: Service Revenues - Dotz Pay
A15: 71999009007 | B15: Tarifa de Inatividade | C15: Gross Revenues | D15: Service Revenues - Dotz Pay
A16: 71799003002 | B16: Tarifa Recarga Celular | C16: Gross Revenues | D16: Service Revenues - Dotz Pay
A17: 71999009005 | B17: Receita de Exclusividade | C17: Gross Revenues | D17: Service Revenues - Dotz Pay
A18: 71799003004 | B18: Comissão EC - MDR | C18: Gross Revenues | D18: Service Revenues - Dotz Pay
A19: 71795227001 | B19: Tarifa de Saque | C19: Gross Revenues | D19: Service Revenues - Dotz Pay
A20: 71999009006 | B20: Receita de Intermediação | C20: Gross Revenues | D20: Service Revenues - Dotz Pay
A21: 71799003005 | B21: Comissão Cartão de Crédito | C21: Gross Revenues | D21: Service Revenues - Dotz Pay
A22: 71705004001 | B22: Tarifa Recarga | C22: Gross Revenues | D22: Service Revenues - Dotz Pay
B23: TOTAL DE AJUSTES
B24: Service Revenues - Noverde
B25: TOTAL DE AJUSTES
B26: (-) Sales Tax & Deductions
B27: Pis
A28: 81933000003 | B28: Pis - Serviços Prestados | C28: (-) Sales Tax & Deductions | D28: Sales Tax
A29: 81933000002 | B29: Pis - Outras Receitas Operacionais | C29: (-) Sales Tax & Deductions | D29: Sales Tax
B30: TOTAL DE AJUSTES
B31: Cofins
A32: 81930003003 | B32: Cofins - Serviços Prestados | C32: (-) Sales Tax & Deductions | D32: Sales Tax
A33: 81930003002 | B33: Cofins- Outras Receitas Operacionai | C33: (-) Sales Tax & Deductions | D33: Sales Tax
B34: TOTAL DE AJUSTES
B35: ISS
A36: 81925001001 | B36: (-) ISS sobre Vendas | C36: (-) Sales Tax & Deductions | D36: Sales Tax
B37: TOTAL DE AJUSTES
B38: Deductions
A39: 81706000002 | B39: (-)Cofins Crédito sobre insumos | C39: (-) Sales Tax & Deductions | D39: Deductions
A40: 81703003002 | B40: (-)Pis Crédito sobre insumos | C40: (-) Sales Tax & Deductions | D40: Deductions
B41: TOTAL DE AJUSTES
B42: (-) Costs
B43: Redemption Cost
B44: TOTAL DE AJUSTES
B45: Coop Media
B46: TOTAL DE AJUSTES
B47: BV & EAN
B48: TOTAL DE AJUSTES
B49: (-) Operational Costs
B50: Other costs - CBSM CAT
B51: TOTAL DE AJUSTES
B52: Other costs - Dotz Pay
A53: 81739008009 | B53: Bank Reconciliation | C53: (-) Operational Costs | D53: Other costs - Dotz Pay
A54: 81739008001 | B54: Processamento de Dados - Conductor | C54: (-) Operational Costs | D54: Other costs - Dotz Pay
A55: 81739008012 | B55: Custo de Prevenção de Fraudes | C55: (-) Operational Costs | D55: Other costs - Dotz Pay
A56: 81120002001 | B56: Despesas Rendimento Conta Remunerada | C56: (-) Operational Costs | D56: Other costs - Dotz Pay
A57: 81739008007 | B57: Onboarding | C57: (-) Operational Costs | D57: Other costs - Dotz Pay
A58: 81739008010 | B58: Embossing | C58: (-) Operational Costs | D58: Other costs - Dotz Pay
A59: 81739008003 | B59: Cash Out | C59: (-) Operational Costs | D59: Other costs - Dotz Pay
A60: 81739008099 | B60: Others Processing Expenses | C60: (-) Operational Costs | D60: Other costs - Dotz Pay
A61: 81120002003 | B61: (-) IRRF sobre conta Remunerada | C61: (-) Operational Costs | D61: Other costs - Dotz Pay
B62: TOTAL DE AJUSTES
B63: Other costs - NoVerde
A64: 81739008004 | B64: Promo Dotz Acquisition | C64: (-) Operational Costs | D64: Other costs - Dotz Pay
B65: TOTAL DE AJUSTES
B66: Gross Profit
B67: %
B68: TOTAL DE AJUSTES
B69: SG&A
B70: Personnel
A71: 81730100001 | B71: Fgts | C71: SG&A | D71: Personnel
A72: 81727003015 | B72: Verbas Rescisórias | C72: SG&A | D72: Personnel
A73: 81733004003 | B73: Triênio | C73: SG&A | D73: Personnel
A74: 81757104031 | B74: Serviços Prestados - PJ | C74: SG&A | D74: Personnel
A75: 81733004002 | B75: Salários | C75: SG&A | D75: Personnel
A76: 81730502001 | B76: Inss | C76: SG&A | D76: Personnel
A77: 81727003018 | B77: Vale Refeição | C77: SG&A | D77: Personnel
A78: 81733004005 | B78: 13° Salário | C78: SG&A | D78: Personnel
A79: 81727003001 | B79: Assistência Médica | C79: SG&A | D79: Personnel
A80: 81727003004 | B80: Seguro de Vida | C80: SG&A | D80: Personnel
A81: 81733004099 | B81: Cost Shering | C81: SG&A | D81: Personnel
A82: 81727003019 | B82: Férias | C82: SG&A | D82: Personnel
A83: 81727003005 | B83: Assistencia Odontologica | C83: SG&A | D83: Personnel
B84: TOTAL DE AJUSTES
B85: Bonus
A86: 81733004009 | B86: PLR | C86: SG&A | D86: Bonus
B87: TOTAL DE AJUSTES
B88: Recruitment & Development People
B89: TOTAL DE AJUSTES
B90: Facilities & Rentals
B91: TOTAL DE AJUSTES
B92: Services
A93: 81763005002 | B93: Assessoria Contábil e Auditoria | C93: SG&A | D93: Services
A94: 81763005001 | B94: Assessoria Jurídica | C94: SG&A | D94: Services
A95: 81769009001 | B95: Taxas Municipais, Estaduais e Federais | C95: SG&A | D95: Services
A96: 81763005003 | B96: Serviços de Consultoria | C96: SG&A | D96: Services
A97: 81724006001 | B97: Gráfica e Impressões | C97: SG&A | D97: Services
B98: TOTAL DE AJUSTES
B99: CRM & Call Center
B100: TOTAL DE AJUSTES
...

Sheet cbsmfornecedor
A1: Código do PN | B1: Nome do PN | C1: CNPJ | D1: Saldo do parceiro de negócios | E1: Parceiro | F1: Início | G1: Cidade | H1: Estado | I1: Número ID | J1: Inativo | K1: POS Estabelecimento | L1: Cod. DOTZ | M1: Característica 16 | N1: Saldo | O1: Nome fantasia | P1: E-mail | Q1: Cod Estab | R1: Rua do destinatário | S1: Moeda do PN | T1: Data de atualização | U1: [Act]-Item Fluxo de Caixa | V1: Moeda padrão | W1: Endereço de cobrança: país/região | X1: Visualizar PN no Portal?
A2: C000001 | B2: A Universal | D2: 0 | F2: 40816 | J2: Y | L2: 43719 | M2: N | N2: 0 | S2: ## | T2: 40949 | V2: Real | W2: Brasil
A3: C000003 | B3: Acabamentos Bel Lar Ltda | C3: 17.311.465/0001-66 | D3: 0 | E3: Bel Lar | F3: 40816 | G3: Belo Horizonte | H3: MG | J3: N | L3: 1564348 | M3: N | N3: 0 | R3: Pedro II | S3: ## | T3: 43355 | V3: Real | W3: Brasil
A4: C000004 | B4: ALTA ENERGIA FRANCHISING LTDA | C4: 08.274.966/0001-29 | D4: 0 | E4: Academia Alta Energia | F4: 40816 | G4: Belo Horizonte | H4: MG | J4: N | L4: 1573280 | M4: N | N4: 0 | P4: comercial@altaenergia.com.br | R4: Dos Inconfidentes | S4: ## | T4: 42578 | V4: Real | W4: Brasil
A5: C000006 | B5: Acf - Correios | D5: 0 | F5: 40816 | J5: Y | L5: 1732963 | M5: N | N5: 0 | S5: ## | T5: 41319 | V5: Real | W5: Brasil
A6: C000008 | B6: Alecred Promotora Negocios Cres Ltda | C6: 09.547.644/0001-79 | D6: 0 | E6: Ale | F6: 40816 | G6: Natal | H6: RN | J6: N | L6: 1077750 | M6: N | N6: 0 | P6: cptrocas@dotz.com | R6: Manoel de Castro | S6: ## | T6: 44019 | V6: Real | W6: Brasil
A7: C000009 | B7: ALESAT COMBUSTIVEIS S.A. | C7: 23.314.594/0001-00 | D7: 0 | E7: Ale | F7: 40816 | G7: NATAL | H7: RN | J7: N | L7: 290058 | M7: N | N7: 0 | P7: jonatas.braz@ale.com.br | R7: MANOEL DE CASTRO 1170 | S7: ## | T7: 43804 | V7: Real | W7: Brasil
A8: C000010 | B8: Decminas Distribuicao e Logistica S.A. | C8: 07.399.636/0001-05 | D8: 0 | E8: APOIO | F8: 40816 | G8: Contagem | H8: MG | J8: N | L8: 1160653 | M8: N | N8: 0 | O8: cptrocas@dotz.com | P8: cptrocas@dotz.com | R8: Trajano Araujo Viana | S8: ## | T8: 42384 | V8: Real | W8: Brasil
A9: C000011 | B9: Ambiental | D9: 0 | F9: 40816 | J9: Y | L9: 43724 | M9: N | N9: 0 | S9: ## | T9: 41327 | V9: Real | W9: Brasil
A10: C000012 | B10: América Comercial Ltda | C10: 54.805.247/0001-04 | D10: 0 | E10: América | F10: 40816 | G10: São Paulo | H10: SP | J10: N | L10: 1468376 | M10: N | N10: 0 | P10: amnvj@restauranteamerica.com.br; vitornascimento@restauranteamerica.com.br | R10: Nove De Julho | S10: ## | T10: 41647 | V10: Real | W10: Brasil
A11: C000013 | B11: Amteas Praia Hotel Ltda | C11: 06.067.156/0001-76 | D11: 0 | E11: Atlantica Hotels | F11: 40816 | G11: Niteroí | H11: RJ | J11: N | L11: 289447 | M11: N | N11: 0 | P11: contasapagar.qnrj@atlanticahotels.com.br | R11: Professor Alvaro Caetano | S11: ## | T11: 42145 | V11: Real | W11: Brasil
A12: C000014 | B12: Anália Franco Serviços De Alimentação Ltda | C12: 03.578.412/0001-00 | D12: 0 | E12: América | F12: 40816 | G12: São Paulo | H12: SP | J12: N | L12: 1468376 | M12: N | N12: 0 | P12: amanf@restauranteamerica.com.br; vitornascimento@restauranteamerica.com.br | R12: Regente Feijo | S12: ## | T12: 41647 | V12: Real | W12: Brasil
A13: C000015 | B13: DECMINAS DISTRIBUICAO E LOGISTICA S.A. | C13: 07.399.636/0002-88 | D13: 0 | E13: APOIO | F13: 40816 | G13: contagem | H13: MG | J13: N | L13: 1451871 | M13: N | N13: 0 | O13: cptrocas@dotz.com | P13: cptrocas@dotz.com | R13: BR-040, KM 688 PV03 | S13: ## | T13: 42619 | V13: Real | W13: Brasil
A14: C000017 | B14: Area Parking | D14: 0 | F14: 40816 | J14: Y | L14: 1013288 | M14: N | N14: 0 | S14: ## | T14: 41319 | V14: Real | W14: Brasil
A15: C000019 | B15: Assist- Card Do Brasil Ltda | C15: 00.027.571/0001-10 | D15: 0 | E15: Assist-Card | F15: 40816 | G15: São Paulo | H15: SP | J15: N | L15: 1584984 | M15: N | N15: 0 | R15: Paulista | S15: ## | T15: 41187 | V15: Real | W15: Brasil
A16: C000021 | B16: Associação Dos Lojistas Leitura Ltda | C16: 07.470.391/0001-57 | D16: 0 | E16: Leitura | F16: 40816 | G16: BELO HORIZONTE | H16: MG | J16: N | L16: 1714099 | M16: N | N16: 0 | P16: renataall@leitura.com.br; oberdan@leitura.com.br | R16: GETULIO VARGAS 668 668 SLJ | S16: ## | T16: 43182 | V16: Real | W16: Brasil
A17: C000023 | B17: Associação Monte Azul | D17: 0 | F17: 40816 | J17: Y | L17: 43728 | M17: N | N17: 0 | S17: ## | T17: 41319 | V17: Real | W17: Brasil
A18: C000024 | B18: Atlantica Hotels Internacional Brasil Ltda | C18: 02.223.966/0001-13 | D18: 80702.81 | E18: Atlantica Hotels | F18: 40816 | G18: BARUERI | H18: SP | J18: N | L18: 290689 | M18: N | N18: 0 | P18: mkthoteis.ahi@atlanticahotels.com.br; gsminatel@atlanticahotels.com.br | R18: RIO NEGRO 585 AND 13 | S18: ## | T18: 45628 | V18: Real | W18: Brasil
A19: C000025 | B19: Atlantica Hotels Internacional Brasil Ltda | C19: 02.223.966/0057-78 | D19: 0 | E19: Atlantica Hotels | F19: 40816 | G19: Brasília | H19: DF | J19: N | L19: 1013296 | M19: N | N19: 0 | R19: SHN | S19: ## | T19: 41415 | V19: Real | W19: Brasil
A20: C000026 | B20: Atlantica Hotels Internacional Brasil Ltda | C20: 02.223.966/0051-82 | D20: 0 | E20: Atlantica Hotels | F20: 40816 | G20: Rio de Janeiro | H20: RJ | J20: N | L20: 1013296 | M20: N | N20: 0 | R20: Barata Ribeiro | S20: ## | T20: 41415 | V20: Real | W20: Brasil
A21: C000027 | B21: ATOMO PROPAGANDA CONVENCOES E EVENTOS LTDA | C21: 05.081.854/0001-63 | D21: 0 | E21: Atomo | F21: 40816 | G21: Santana de Parnaíba | H21: SP | J21: N | L21: 1592264 | M21: N | N21: 0 | R21: Tchucaramanis | S21: ## | T21: 41375 | V21: Real | W21: Brasil
A22: C000028 | B22: Automax Comercial Ltda | C22: 20.994.976/0001-34 | D22: 0 | E22: Automax | F22: 40816 | G22: Belo Horizonte | H22: MG | J22: N | L22: 1157149 | M22: N | N22: 0 | P22: eliana@automaxfiat.com.br; edvania@automaxfiat.com.br | R22: Raja Gabaglia | S22: ## | T22: 43082 | V22: Real | W22: Brasil
A23: C000029 | B23: Azul Music | C23: 71.874.077/0001-39 | D23: 0 | F23: 40816 | G23: SAO PAULO | H23: SP | J23: Y | L23: 1401633 | M23: N | N23: 0 | R23: FERNANDES MOREIRA | S23: ## | T23: 41327 | V23: Real | W23: Brasil
A24: C000030 | B24: Azul Music | D24: 0 | F24: 40816 | J24: Y | L24: 1401633 | M24: N | N24: 0 | S24: ## | T24: 41319 | V24: Real | W24: Brasil
A25: C000031 | B25: AMERICANAS S.A - EM RECUPERACAO JUDICIAL | C25: 00.776.574/0006-60 | D25: 495180.12 | E25: AMERICANAS | F25: 40816 | G25: Rio de Janeiro | H25: RJ | J25: N | L25: 1013253 | M25: N | N25: 0 | R25: Sacadura Cabral | S25: ## | T25: 45964 | V25: Real | W25: Brasil
A26: C000032 | B26: AMERICANAS S.A. | C26: 00.776.574/0006-60 | D26: 0 | E26: Submarino | F26: 40816 | G26: Rio de Janeiro | H26: RJ | J26: N | L26: 1006739 | M26: N | N26: 0 | R26: Sacadura Cabral | S26: ## | T26: 44410 | V26: Real | W26: Brasil
A27: C000033 | B27: B2W - Companhia Global Do Varejo | C27: 00.776.574/0001-56 | D27: 0 | E27: Submarino | F27: 40816 | G27: Osasco | H27: SP | J27: N | L27: 10650156 | M27: N | N27: 0 | R27: Henry Ford | S27: ## | T27: 44999 | V27: Real | W27: Brasil
A28: C000034 | B28: B2W Companhia Global Do Varejo | C28: 00.776.574/0007-41 | D28: 0 | E28: Americanas.com | F28: 40816 | G28: Itapevi | H28: SP | J28: N | L28: 290123 | M28: N | N28: 0 | P28: rodrigo.reis@b2wdigital.com; myrian.lamm@b2wdigital.com | R28: Estrada dos Alpes | S28: ## | T28: 42863 | V28: Real | W28: Brasil
A29: C000035 | B29: Bag-Online Comércio De Bolsas Ltda | C29: 08.956.394/0001-68 | D29: 0 | E29: Bagaggio | F29: 40816 | G29: Rio de Janeiro | H29: RJ | J29: N | L29: 1144839 | M29: N | N29: 0 | P29: Renata.vilar@bagaggi.com.br;Bruno.oliveira@bagaggio.com.br | R29: Santo Cristo | S29: ## | T29: 41529 | V29: Real | W29: Brasil
A30: C000036 | B30: Banco Bankpar S/A | C30: 60.419.645/0006-08 | D30: 0 | E30: Amex | F30: 40816 | G30: Barueri | H30: SP | J30: N | L30: 1013269 | M30: N | N30: 0 | R30: Rio Negro | S30: ## | T30: 41375 | V30: Real | W30: Brasil
A31: C000037 | B31: Banco Do Brasil S.A. | C31: 00.000.000/0001-91 | D31: 6796215.1 | E31: BB | F31: 40816 | G31: Brasília | H31: DF | J31: N | L31: 1153615 | M31: N | N31: 0 | R31: BANCARIO SUL | S31: ## | T31: 45887 | V31: Real | W31: Brasil
A32: C000038 | B32: Banco Hsbc - Crédito Imobiliário | D32: 0 | F32: 40816 | J32: Y | L32: 1132624 | M32: N | N32: 0 | S32: ## | T32: 41319 | V32: Real | W32: Brasil
A33: C000039 | B33: Banco Bradescard S/A | C33: 04.184.779/0001-01 | D33: 0 | E33: Bradescard | F33: 40816 | G33: Barueri | H33: SP | J33: N | L33: 17942467 | M33: N | N33: 0 | P33: karina.novaes@bradesco.com.br | R33: Rio Negro | S33: ## | T33: 44230 | V33: Real | W33: Brasil
A34: C000040 | B34: Banco Ibi S/A - Banco Múltiplo | C34: 04.184.779/0001-01 | D34: 0 | E34: IBI - Cartão Dotz | F34: 40816 | G34: Barueri | H34: SP | J34: N | L34: 1748523 | M34: N | N34: 0 | P34: sonia.mattos@ibi.com.br | R34: Rio Negro | S34: ## | T34: 42578 | V34: Real | W34: Brasil
A35: C000041 | B35: Bar E Restaurante Acirema Ltda | C35: 05.620.415/0001-81 | D35: 0 | E35: América | F35: 40816 | G35: São Paulo | H35: SP | J35: N | L35: 1468376 | M35: N | N35: 0 | P35: ampta@restauranteamerica.com.br; vitornascimento@restauranteamerica.com.br | R35: Paulista | S35: ## | T35: 41647 | V35: Real | W35: Brasil
A36: C000042 | B36: Bar E Restaurante Alp Ltda | C36: 02.700.119/0001-00 | D36: 0 | E36: América | F36: 40816 | G36: São Paulo | H36: SP | J36: N | L36: 1468376 | M36: N | N36: 0 | P36: amalp@restauranteamerica.com.br; vitornascimento@restauranteamerica.com.br | R36: Mamore | S36: ## | T36: 41647 | V36: Real | W36: Brasil
A37: C000043 | B37: Bar E Restaurante Als Ltda | C37: 58.231.580/0001-08 | D37: 0 | E37: América | F37: 40816 | G37: São Paulo | H37: SP | J37: N | L37: 1468376 | M37: N | N37: 0 | P37: amals@restauranteamerica.com.br; vitornascimento@restauranteamerica.com.br | R37: Santos | S37: ## | T37: 41647 | V37: Real | W37: Brasil
A38: C000044 | B38: Bar E Restaurante Appl Ltda | C38: 05.660.039/0001-59 | D38: 0 | E38: América | F38: 40816 | G38: São Paulo | H38: SP | J38: N | L38: 1468376 | M38: N | N38: 0 | P38: amvlb@restauranteamerica.com.brvitornascimento@restauranteamerica.com.br | R38: Das Nações Unidas | S38: ## | T38: 41647 | V38: Real | W38: Brasil
A39: C000045 | B39: bar e restaurante bsp | C39: 09.109.965/0001-91 | D39: 0 | E39: América | F39: 40816 | G39: São Paulo | H39: SP | J39: N | L39: 1468376 | M39: N | N39: 0 | P39: ambsp@restauranteamerica.com.br; vitornascimento@restauranteamerica.com.br | R39: Turiassu | S39: ## | T39: 41647 | V39: Real | W39: Brasil
A40: C000046 | B40: Bar E Restaurante Ctn Ltda | C40: 61.990.354/0001-15 | D40: 0 | E40: América | F40: 40816 | G40: São Paulo | H40: SP | J40: N | L40: 1468376 | M40: N | N40: 0 | P40: amctn@restauranteamerica.com.br; vitornascimento@restauranteamerica.com.br | R40: Casalbuono | S40: ## | T40: 41647 | V40: Real | W40: Brasil
A41: C000048 | B41: Bar E Restaurante Igt Ltda | C41: 59.305.417/0001-05 | D41: 0 | E41: América | F41: 40816 | G41: São Paulo | H41: SP | J41: N | L41: 1468376 | M41: N | N41: 0 | P41: amigt@restauranteamerica.com.br; vitornascimento@restauranteamerica.com.br | R41: Brigadeiro Faria Lima | S41: ## | T41: 41647 | V41: Real | W41: Brasil
A42: C000049 | B42: Bar E Restaurante Mrb Ltda | C42: 60.039.328/0001-43 | D42: 0 | E42: América | F42: 40816 | G42: São Paulo | H42: SP | J42: N | L42: 1468376 | M42: N | N42: 0 | P42: ammrb@restauranteamerica.com.br; vitornascimento@restauranteamerica.com.br; vitornascimento@restaura | R42: Roque Petroni Junior | S42: ## | T42: 43042 | V42: Real | W42: Brasil
A43: C000050 | B43: Be Cosméticos Distribuição E Representação Comercial | C43: 11.501.262/0001-56 | D43: 0 | E43: Be Cosméticos | F43: 40816 | G43: Contagem | H43: MG | J43: N | L43: 1728701 | M43: N | N43: 0 | R43: Um | S43: ## | T43: 40917 | V43: Real | W43: Brasil
A44: C000051 | B44: Beach Park | D44: 0 | F44: 40816 | J44: Y | L44: 1013299 | M44: N | N44: 0 | S44: ## | T44: 41319 | V44: Real | W44: Brasil
A45: C000052 | B45: Beach Park Wellness Resort | D45: 0 | F45: 40816 | J45: Y | L45: 1013322 | M45: N | N45: 0 | S45: ## | T45: 41319 | V45: Real | W45: Brasil
A46: C000055 | B46: Bffc Do Brasil Participações Ltda | C46: 07.720.382/0001-77 | D46: 0 | E46: Bob's | F46: 40816 | G46: Rio de Janeiro | H46: RJ | J46: N | L46: 1013315 | M46: N | N46: 0 | R46: Voluntários da Pátria | S46: ## | T46: 42390 | V46: Real | W46: Brasil
A47: C000056 | B47: Bichomania | D47: 0 | F47: 40816 | J47: Y | L47: 43866 | M47: N | N47: 0 | S47: ## | T47: 41319 | V47: Real | W47: Brasil
A48: C000057 | B48: Bikas 2000 Ltda | C48: 03.492.348/0001-31 | D48: 0 | E48: Bikas | F48: 40816 | G48: Belo Horizonte | H48: MG | J48: N | L48: 1363338 | M48: N | N48: 0 | R48: dos Carijós | S48: ## | T48: 41375 | V48: Real | W48: Brasil
A49: C000059 | B49: Bradesco Auto/Re Companhia De Seguros | C49: 92.682.038/0001-00 | D49: 0 | E49: Ibi - Incentivos | F49: 40816 | G49: Rio de Janeiro | H49: RJ | J49: N | L49: 1748523 | M49: N | N49: 0 | R49: Barão De Itapagipe | S49: ## | T49: 40917 | V49: Real | W49: Brasil
A50: C000060 | B50: Bradesco Vida E Previdencia S/A | C50: 51.990.695/0001-37 | D50: 0 | E50: Ibi - Incentivos | F50: 40816 | G50: Osasco | H50: SP | J50: N | L50: 1748523 | M50: N | N50: 0 | P50: contfiscal@bradescoseguros.com.br | R50: Cidade De Deus | S50: ## | T50: 40917 | V50: Real | W50: Brasil
A51: C000061 | B51: Bud Comercio De Eletrodomesticos Ltda | C51: 62.058.318/0007-76 | D51: 0 | E51: Compra Certa | F51: 40816 | G51: São Paulo | H51: SP | J51: N | L51: 1669356 | M51: N | N51: 0 | P51: josemar_b_junior@d2cwhp.com;veluma_gomes_messias_algar@d2cwhp.com | R51: Olympia Semeraro | S51: ## | T51: 44421 | V51: Real | W51: Brasil
A52: C000063 | B52: C&C Casa E Construção Ltda | C52: 63.004.030/0001-96 | D52: 0 | E52: C&C | F52: 40816 | G52: São Paulo | H52: SP | J52: N | L52: 290096 | M52: N | N52: 0 | P52: lais.lombardo@cec.com.br; silvia@cec.com.br | R52: Miguel Estéfano | S52: ## | T52: 41464 | V52: Real | W52: Brasil
A53: C000064 | B53: Caçula De Pneus Comércio, Importação E Exportação Ltda | C53: 60.740.651/0001-40 | D53: 0 | E53: Caçula De Pneus | F53: 40816 | G53: São Paulo | H53: SP | J53: N | L53: 1013282 | M53: N | N53: 0 | R53: Santo Amaro | S53: ## | T53: 41330 | V53: Real | W53: Brasil
A54: C000066 | B54: MAXMIX COMERCIAL LTDA | C54: 03.002.339/0009-72 | D54: 0 | E54: Camicado | F54: 40816 | G54: SAO PAULO | H54: SP | J54: Y | L54: 1466491 | M54: N | N54: 0 | R54: Roque Petroni Junior | S54: ## | T54: 41327 | V54: Real | W54: Brasil
A55: C000067 | B55: Campanha Tim - Digipronto | D55: 0 | F55: 40816 | J55: Y | L55: 1719598 | M55: N | N55: 0 | S55: ## | T55: 41319 | V55: Real | W55: Brasil
A56: C000071 | B56: Carlton Plaza São José Dos Campos | C56: 03.992.359/0001-80 | D56: 0 | E56: Atlantica Hotels | F56: 40816 | G56: São José dos Campos | H56: SP | J56: N | L56: 290704 | M56: N | N56: 0 | P56: financeirosjc@carltonhoteis.com.br; ggeral.cjcp@atlanticahotels.com.br | R56: Presidente Bernardes | S56: ## | T56: 42452 | V56: Real | W56: Brasil
A57: C000074 | B57: Celi Empreendimentos Hoteleiros Ltda | C57: 05.126.381/0001-73 | D57: 0 | E57: Atlantica Hotels | F57: 40816 | G57: Aracaju | H57: SE | J57: N | L57: 289443 | M57: N | N57: 0 | P57: controller.qaju@atlanticahotels.com.br | R57: Delmiro Golveia | S57: ## | T57: 42219 | V57: Real | W57: Brasil
A58: C000078 | B58: Cheque Teatro | D58: 0 | F58: 40816 | J58: Y | L58: 43731 | M58: N | N58: 0 | S58: ## | T58: 41319 | V58: Real | W58: Brasil
A59: C000082 | B59: Citibank | D59: 0 | F59: 40816 | J59: Y | L59: 1013265 | M59: N | N59: 0 | S59: ## | T59: 41319 | V59: Real | W59: Brasil
A60: C000083 | B60: Clinck Turismo Ltda Me | C60: 09.339.553/0001-48 | D60: 0 | E60: Clinck Turismo | F60: 40816 | G60: Belo Horizonte | H60: MG | J60: N | L60: 96 | M60: N | N60: 0 | R60: Viamão | S60: ## | T60: 41332 | V60: Real | W60: Brasil
A61: C000084 | B61: Comercial Dahana Ltda | C61: 00.070.509/0002-91 | D61: 0 | E61: Xuá | F61: 40816 | G61: Belo Horizonte | H61: MG | J61: N | L61: 1160653 | M61: N | N61: 0 | O61: cptrocas@dotz.com | P61: cptrocas@dotz.com | R61: BR- 356 | S61: ## | T61: 41375 | V61: Real | W61: Brasil
A62: C000085 | B62: CONDOMINIO DO COMPLEXO IMOBILIARIO PARAGEM | C62: 07.615.240/0001-40 | D62: 0 | E62: Shopping Paragem | F62: 40816 | G62: Belo Horizonte | H62: MG | J62: N | L62: 1697984 | M62: N | N62: 0 | R62: Professor Mário Werneck | S62: ## | T62: 41529 | V62: Real | W62: Brasil
A63: C000088 | B63: Criatura Brasil | C63: 10.835.324/0001-01 | D63: 0 | F63: 40816 | G63: BELO HORIZONTE | H63: MG | J63: Y | L63: 1466508 | M63: N | N63: 0 | R63: R ITAPEMA | S63: ## | T63: 41333 | V63: Real | W63: Brasil
A64: C000089 | B64: Csu Cardsystem S/A | C64: 01.896.779/0001-38 | D64: 0 | E64: Card System | F64: 40816 | G64: Barueri | H64: SP | J64: N | L64: 95 | M64: N | N64: 0 | R64: Piauí | S64: ## | T64: 41199 | V64: Real | W64: Brasil
A65: C000092 | B65: Cvc Matriz | C65: 10.760.260/0001-19 | D65: 0 | E65: CVC | F65: 40816 | G65: Santo André | H65: SP | J65: Y | L65: 1683849 | M65: N | N65: 0 | R65: DAS FIGUEIRAS | S65: ## | T65: 41330 | V65: Real | W65: Brasil
A66: C000093 | B66: JPG VIAGENS E TURISMO LTDA - ME | C66: 10.345.578/0001-33 | D66: 0 | E66: JPTUR | F66: 40816 | G66: SAO PAULO | H66: SP | J66: Y | L66: 1558195 | M66: N | N66: 0 | R66: JAPURUCHITA | S66: ## | T66: 41327 | V66: Real | W66: Brasil
A67: C000094 | B67: D&P Serviços De Informática E Fotografia Ltda | C67: 11.753.396/0001-64 | D67: 0 | E67: Retes | F67: 40816 | G67: Belo Horizonte | H67: MG | J67: Y | L67: 1160372 | M67: N | N67: 0 | R67: do Ouro | S67: ## | T67: 41333 | V67: Real | W67: Brasil
A68: C000095 | B68: Das Consultoria Ltda | C68: 04.960.140/0001-62 | D68: 0 | E68: Iformação | F68: 40816 | G68: São Paulo | H68: SP | J68: N | L68: 1409897 | M68: N | N68: 0 | R68: Senador Milton Campos | S68: ## | T68: 40917 | V68: Real | W68: Brasil
A69: C000096 | B69: Daylight Filmes | D69: 0 | F69: 40816 | J69: Y | L69: 43821 | M69: N | N69: 0 | S69: ## | T69: 41319 | V69: Real | W69: Brasil
A70: C000097 | B70: De Pasqual Hotéis E Turismo Ltda | C70: 05.424.423/0001-52 | D70: 0 | E70: Atlantica Hotels | F70: 40816 | G70: Manaus | H70: AM | J70: N | L70: 1013296 | M70: N | N70: 0 | P70: rabranches@atlanticahotels.com.br; controller.cmao@atlanticahotels.com.br | R70: Mandii | S70: ## | T70: 42314 | V70: Real | W70: Brasil
A71: C000098 | B71: Delta Filmes Ltda | C71: 01.735.159/0001-17 | D71: 0 | E71: Delta Filmes | F71: 40816 | G71: Belo Horizonte | H71: MG | J71: N | L71: 98 | M71: N | N71: 0 | P71: liliane.lopes@cineart.com.br | R71: Presidente Carlos Luz | S71: ## | T71: 41389 | V71: Real | W71: Brasil
A72: C000099 | B72: Delta Prime | D72: 0 | F72: 40816 | J72: Y | L72: 43771 | M72: N | N72: 0 | S72: ## | T72: 41319 | V72: Real | W72: Brasil
A73: C000100 | B73: Dese Desenvolvimento De Sistemas | C73: 19.702.463/0001-23 | D73: 0 | E73: Luziana Lanna | F73: 40816 | G73: Belo Horizonte | H73: MG | J73: N | L73: 1693828 | M73: N | N73: 0 | P73: assessoria@luzianalanna.com.br | R73: Edigard Coelho | S73: ## | T73: 42578 | V73: Real | W73: Brasil
A74: c0001000 | B74: Leitura Estação BH Ltda | C74: 15.118.187/0003-61 | D74: 0 | E74: Leitura | F74: 41606 | G74: Contagem | H74: MG | J74: N | L74: 1714099 | M74: N | N74: 0 | P74: cxcentralcontagem@leitura.com.br | R74: Severino Ballesteros Rodrigues | S74: Real | T74: 43147 | W74: Brasil
A75: c0001001 | B75: Leitura Campinas Ltda | C75: 18.269.846/0001-97 | D75: 0 | E75: Leitura | F75: 41606 | G75: CAMPINAS | H75: SP | J75: N | L75: 1714099 | M75: N | N75: 0 | P75: cxcentralcampinas2@leitura.com.br | R75: JACY TEIXEIRA CAMARGO 940 309 310 | S75: Real | T75: 42709 | W75: Brasil
A76: C000100100 | B76: Magazine Luiza S/A | C76: 47960950085445 | D76: 0 | E76: Magazine Luiza | F76: 41969 | G76: Fortaleza | H76: CE | J76: N | L76: Obrigatório | M76: N | N76: 0 | P76: 809@magazineluiza.com.br | R76: Barao do Rio Branco | S76: Real | T76: 42578 | W76: Brasil
A77: c00010017 | B77: ATACADÃO DOS ELETRODOMESTICOS DO NORDESTE LTDA | C77: 70.120.662/0001-80 | D77: 0 | E77: Atacadão dos Eletros | F77: 41845 | G77: Joao Pessoa | H77: PB | J77: N | L77: 17183223 | M77: N | N77: 0 | P77: freitas@atacadaodoseletros.net; contasapagar@atacadaodoseletros.net; alana@atacadaodoseletros.net; | R77: BR-101 | S77: Real | T77: 42677 | W77: Brasil
A78: c00010018 | B78: MEET COMÉRCIO DE ALIMENTOS LTDA | C78: 19.162.215/0001-37 | D78: 0 | E78: SUSHILOKO | F78: 41849 | G78: BRASILIA | H78: DF | J78: N | L78: 1760189 | M78: N | N78: 0 | P78: eduardojoc@gmail.com; tomas.de.paiva@gmail.com | R78: SDN CONJ. A LJ.2135-A 2º PAV. | S78: Real | T78: 42429 | W78: Brasil
A79: c00010019 | B79: Loja 03 - ÓTIMA COMÉRCIO DE ALIMENTOS S/A FILIAL | C79: 13.197.254/0002-74 | D79: 0 | E79: UltraBox | F79: 41849 | G79: Brasilia | H79: DF | J79: N | L79: 14791297 | M79: N | N79: 0 | P79: fabio@bigbox.com.br;thaylla@bigbox.com.br | R79: DF-150 | S79: Real | T79: 43802 | W79: Brasil
A80: c0001002 | B80: HHS VÍDEO LOCADORA DE FITAS E DVD LTDA | C80: 07.067.237/0001-39 | D80: 0 | E80: Videoteca | F80: 41607 | G80: Itajai | H80: SC | J80: N | L80: 13433572 | M80: N | N80: 0 | P80: itajaicentro@videotecaonline.com.br; hudsonhhs@hotmail.com | R80: Brusque | S80: Real | T80: 42165 | W80: Brasil
A81: c00010020 | B81: Conquista Fortaleza Lanchonetes Ltda | C81: 06.165.208/0029-48 | D81: 0 | E81: Bob's | F81: 41857 | G81: Maracanau | H81: CE | J81: N | L81: 1013315 | M81: N | N81: 0 | P81: financeiro@conquistafortaleza.com.br | R81: Carlos Jereissati | S81: Real | T81: 41857 | W81: Brasil
A82: c00010021 | B82: POSTO ALPES LTDA | C82: 21.105.457/0001-30 | D82: 0 | E82: POSTO ALPES | F82: 41857 | G82: Belo Horizonte | H82: MG | J82: N | L82: 17304642 | M82: N | N82: 0 | P82: ernesto@grupoccc.com.br | R82: Padre Eustaquio | S82: Real | T82: 42019 | W82: Brasil
A83: c00010022 | B83: Grenadine Comercial Ltda.-ME | C83: 15.382.742/0001-04 | D83: 0 | E83: Grenadine.com.br | F83: 41862 | G83: Osasco | H83: SP | J83: N | L83: 12560092 | M83: N | N83: 0 | P83: andressa@grenadine.com.br | R83: Alberto Cortez | S83: Real | W83: Brasil
A84: c00010023 | B84: QG FRANCHISING SERV DE GESTÃO EM FRANQUIAS LTDA | C84: 11.146.451/0001-58 | D84: 0 | E84: QG Jeitinho Caseiro | F84: 41862 | G84: Goiânia | H84: GO | J84: N | L84: 17357601 | M84: N | N84: 0 | P84: pedropaulo@grupoqg.com.br; financeiro@grupoqg.com.br | R84: Santo Antônio | S84: Real | T84: 42230 | W84: Brasil
A85: c00010024 | B85: TELEFÔNICA BRASIL S.A. | C85: 02.558.157/0001-62 | D85: 0 | E85: Vivo | F85: 41862 | G85: São Paulo | H85: SP | J85: N | L85: 1015494 | M85: N | N85: 0 | P85: ENVIAR FATURA PELO CORREIO OU MOTOBOY | R85: Engenheiro Luiz Carlos Berrini | S85: Real | T85: 43313 | W85: Brasil
A86: c00010025 | B86: DIAMANTE COMÉRCIO DE CALÇADOS LTDA | C86: 04.685.920/0001-41 | D86: 0 | E86: Casas Ajita | F86: 41869 | G86: Arapongas | H86: PR | J86: N | L86: 13069406 | M86: N | N86: 0 | P86: diamante@casasajita.com.br; diamante_estoque@casasajita.com.br | R86: Arapongas | S86: Real | T86: 42949 | W86: Brasil
A87: c00010026 | B87: Y.AGITA COMÉRCIO DE CALÇADOS LTDA | C87: 02.701.939/0003-70 | D87: 0 | E87: Casas Ajita | F87: 41869 | G87: Ibiporã | H87: PR | J87: N | L87: 13069406 | M87: N | N87: 0 | P87: ibipora@casasajita.com.br | R87: Paraná | S87: Real | T87: 42949 | W87: Brasil
A88: c00010027 | B88: AMETISTA COMÉRCIO DE CALÇADOS LTDA | C88: 03.158.225/0001-69 | D88: 0 | E88: Casas Ajita | F88: 41869 | G88: Rolândia | H88: PR | J88: N | L88: 13069406 | M88: N | N88: 0 | P88: ametista@casasajita.com.br | R88: Interventor Manoel Ribas | S88: Real | T88: 42949 | W88: Brasil
A89: c00010028 | B89: PASSARELA MODAS LTDA | C89: 45.512.555/0028-70 | D89: 0 | E89: Passarela.com | F89: 41870 | G89: Jundiai | H89: SP | J89: N | L89: 17747286 | M89: N | N89: 0 | P89: livia.marketing@passarela.com.br; midia@passarela.com.br | R89: Osmundo dos Santos Pellegrini | S89: Real | T89: 43598 | W89: Brasil
A90: c00010029 | B90: BIM BAM JOIAS E RELOGIOS LTDA | C90: 75.113.969/0001-78 | D90: 0 | E90: Óticas Gouveia | F90: 41876 | G90: Maringa | H90: PR | J90: N | L90: 17904912 | M90: N | N90: 0 | P90: gouveiamga@hotmail.com; contasapagargouveia@gmail.com | R90: Brasil | S90: Real | T90: 42507 | W90: Brasil
A91: c00010030 | B91: CLERMONT PRESENTES LTDA | C91: 03.303.442/0001-03 | D91: 0 | E91: Óticas Gouveia | F91: 41876 | G91: Maringa | H91: PR | J91: N | L91: 17904912 | M91: N | N91: 0 | P91: gouveiamga@hotmail.com | R91: Brasil | S91: Real | T91: 42467 | W91: Brasil
A92: c00010031 | B92: DGZ ARMARINHOS LTDA | C92: 82.671.819/0001-45 | D92: 0 | E92: Óticas Gouveia | F92: 41876 | G92: Maringa | H92: PR | J92: N | L92: 17904912 | M92: N | N92: 0 | P92: gouveiamga@hotmail.com | R92: Rio Branco | S92: Real | T92: 42179 | W92: Brasil
A93: c00010032 | B93: DYELNI PRESENTES LTDA | C93: 82.308.651/0001-08 | D93: 0 | E93: Óticas Gouveia | F93: 41876 | G93: Maringa | H93: PR | J93: N | L93: 17904912 | M93: N | N93: 0 | P93: gouveiamga@hotmail.com | R93: Sao Paulo | S93: Real | T93: 42467 | W93: Brasil
A94: c00010033 | B94: FOKAS PRESENTES LTDA - ME | C94: 00.190.582/0001-16 | D94: 0 | E94: Óticas Gouveia | F94: 41876 | G94: Maringa | H94: PR | J94: N | L94: 17904912 | M94: N | N94: 0 | P94: gouveiamga@hotmail.com | R94: Brasil | S94: Real | T94: 42467 | W94: Brasil
A95: c00010034 | B95: MONTANE PRESENTES LTDA | C95: 04.614.508/0001-30 | D95: 0 | E95: Óticas Gouveia | F95: 41876 | G95: Maringa | H95: PR | J95: N | L95: 17904912 | M95: N | N95: 0 | P95: gouveiamga@hotmail.com | R95: Brasil | S95: Real | T95: 42467 | W95: Brasil
... A123: c00010061 | B123: JUJU AUTOPEÇAS E COMBUSTIVEIS LTDA | C123: 03.267.340/0001-71 | D123: 0 | E123: Centro Automotivo Colina | F123: 41921 | G123: Mariana | H123: MG | J123: N | L123: 18298205 | M123: N | N123: 0 | P123: postoshellcolina2018@gmail.com;jozimar@redeshellinconfidentes | R123: Pernambuco | S123: Real | T123: 44421 | W123: Brasil
A124: c00010062 | B124: POSTO TOPÁZIO IMPERIAL LTDA | C124: 20.446.027/0001-10 | D124: 0 | E124: Posto Topázio | F124: 41921 | G124: Ouro Preto | H124: MG | J124: N | L124: 18298223 | M124: N | N124: 0 | P124: ptopazio@intercampo.com.br | R124: BR 356 km | S124: Real | W124: Brasil
A125: c00010063 | B125: ZINGA BAR E RESTAURANTE LTDA - ME | C125: 11.052.565/0001-39 | D125: 0 | E125: CAMARÃO DA ILHA | F125: 41921 | G125: Florianopolis | H125: SC | J125: N | L125: 17253430 | M125: N | N125: 0 | P125: administrativo@camaraodailha.com.br | R125: Dom Joao Becker | S125: Real | W125: Brasil
A126: c00010064 | B126: Sá Cavalcante Comestíveis Ltda | C126: 28.410.090/0001-08 | D126: 0 | E126: Bob's | F126: 41921 | G126: Vila Velha | H126: ES | J126: N | L126: 1013315 | M126: N | N126: 0 | P126: imelo@sacavalcante.com.br;mcrespo@sacavalcante.com.br | R126: Doutor Olivio Lira | S126: Real | T126: 43185 | W126: Brasil
A127: c00010065 | B127: Auto Posto Escola Comércio de Combustíveis, Lubrificantes e Serviços Ltda | C127: 16.577.742/0001-14 | D127: 0 | E127: Rede Marcela | F127: 41922 | G127: Vitoria | H127: ES | J127: N | L127: 18306520 | M127: N | N127: 0 | P127: posto.escola@redemarcela.com.br | R127: Americo Buaiz | S127: Real | T127: 42681 | W127: Brasil
...

Sheet dotzfornecedor
A1: Código do PN | B1: Nome do PN | C1: Saldo da conta | D1: CNPJ | E1: [Act]-Item Fluxo de Caixa | F1: Data de atualização
A2: C000001 | B2: Zurich Seguros | C2: 0 | E2: 2 | F2: 45791
A3: F000001 | B3: PROFIC ACCOUNTING & CONSULTING LTDA | C3: 0 | E3: 12 | F3: 45791
A4: F000002 | B4: MZ CONSULT - SERVICOS E NEGOCIOS LTDA | C4: 0 | E4: 12 | F4: 45791
A5: F000003 | B5: ERNST & YOUNG AUDITORES INDEPENDENTES S/S | C5: 0 | E5: 12 | F5: 45791
A6: F000004 | B6: ITAU CORRETORA DE VALORES S/A | C6: 0 | E6: 12 | F6: 45791
A7: F000005 | B7: REAL SRR SP PUBLICIDADE E MARKETING LTDA | C7: 0 | E7: 12 | F7: 45791
A8: F000006 | B8: BANCO BTG PACTUAL S.A. | C8: -10902.04 | E8: 12 | F8: 45791
A9: F000007 | B9: B3 S.A. - BRASIL, BOLSA, BALCAO | C9: 0 | E9: 12 | F9: 45791
A10: F000008 | B10: PINHEIRO NETO ADVOGADOS | C10: 0 | E10: 12 | F10: 45791
A11: F000009 | B11: POWER FINANCIAL DO BRASIL S.A | C11: 0 | F11: 44383
A12: F000010 | B12: BW DOCUMENTOS LEGAIS E SERVICOS DE TECNOLOGIA LTDA | C12: 0 | F12: 44390
A13: F000011 | B13: TORRE DE BABEL SERVICOS DE TRADUCOES JURIDICAS LTDA. | C13: 0
A14: F000012 | B14: QUATA CONFIDENCE CAPITAL ASSESSORIA FINANCEIRA LTDA | C14: 0 | F14: 45374
A15: F000013 | B15: TA IDIOMAS LTDA | C15: 0 | F15: 44455
A16: F000014 | B16: MANUCCI ADVOGADOS | C16: 0 | E16: 12 | F16: 45791
A17: F000015 | B17: DOTZ S/A | C17: -226.68 | E17: 12 | F17: 45791
A18: F000016 | B18: TARGET SERVICOS TECNICOS LTDA | C18: 0 | E18: 12 | F18: 45791
A19: F000017 | B19: LD TRANSLATIONS EIRELI | C19: 0 | F19: 45374
A20: F000018 | B20: SIMPSON THACHER & BARTLETT LLP CONSULTORES EM DIREITO ESTRANGEIRO / DIREITO NORTE-AMERICANO | C20: 0 | E20: 12 | F20: 45791
A21: F000019 | B21: CORREIA, FLEURY, GAMA E SILVA SOCIEDADE DE ADVOGADOS | C21: 0 | E21: 12 | F21: 45791
A22: F000020 | B22: CAMARA DE COMERCIO BRASIL CANADA | C22: 0 | F22: 45374
A23: F000021 | B23: MACHADO MEYER,SENDACZ E OPICE ADVOGADOS | C23: 0 | E23: 12 | F23: 45791
A24: F000022 | B24: GUSTAVO GONZALEZ ADVOGADOS | C24: 0 | E24: 12 | F24: 45791
A25: F000023 | B25: ACTION SYSTEMS SERVICOS EM INFORMATICA LTDA | C25: -13482.79 | E25: 19 | F25: 45791
A26: F000024 | B26: Statista Inc | C26: 0
A27: F000025 | B27: BDO RCS GESTAO EMPRESARIAL LTDA | C27: 0 | F27: 45374
A28: F000026 | B28: TOWERS WATSON CONSULTORIA LTDA | C28: 0 | E28: 12 | F28: 45791
A29: F000027 | B29: DAVIS POLK & WARDWELL CONSULTORES EM DIREITO ESTRANGEIRO / DIREITO NORTE-AMERICANO, | C29: 0 | F29: 45374
A30: F000028 | B30: ACCOUNTFY SERVIÇO DE SOFTWARE LTDA | C30: 0 | E30: 19 | F30: 45791
A31: F000029 | B31: BTG PACTUAL CORRETORA DE TITULOS E VALORES MOBILIARIOS S.A | C31: 0 | F31: 45374
A32: F000030 | B32: Integration Consultoria Empresarial Ltda | C32: 0 | F32: 45374
A33: F000031 | B33: XTPG SISTEMAS DE INFORMACOES LTDA | C33: -8648.53 | E33: 19 | F33: 45791
A34: F000032 | B34: OLIVER WYMAN CONSULTORIA EM ESTRATEGIA DE NEGOCIOS LTDA | C34: 0 | F34: 45374
A35: F000033 | B35: BMG Seguros S.A. | C35: 0 | F35: 45374
A36: F000034 | B36: JA Forte Tecnologia | C36: 0 | F36: 45374
A37: F000035 | B37: ROBERTO TEIXEIRA ARMIJO JUNIOR 12796780899 | C37: 0 | F37: 45374
A38: F000036 | B38: Pinheiro Guimarães | C38: 0 | E38: 12 | F38: 45791
A39: F000037 | B39: VCS CERTIFICACAO E SERVICOS LTDA | C39: -200 | E39: 12 | F39: 45791
A40: F000038 | B40: RDM TECHNOLOGY LTDA | C40: 0 | F40: 45817
A41: F000039 | B41: RSM BRASIL BPS SERVICOS CONTABEIS LTDA | C41: 0 | F41: 45374
A42: F000040 | B42: JUST TRADUCOES S.S. LTDA | C42: 0 | F42: 45374
A43: F000041 | B43: SOUL CAPITAL CONSULTORIA E SERVICOS FINANCEIROS LTDA. | C43: 0 | F43: 45374
A44: F000042 | B44: AIG SEGUROS BRASIL S.A. | C44: 0 | F44: 45374
A45: F000043 | B45: LIBERTY SEGUROS S/A | C45: 0 | F45: 45374
A46: F000044 | B46: HIGASI CONTABILIDADE S/S - EPP | C46: -1891.08 | F46: 45691
A47: F000045 | B47: CHADE E ADVOGADOS ASSOCIADOS | C47: 0 | E47: 19 | F47: 45791
A48: F000046 | B48: MAZARS AUDITORES INDEPENDENTES - SOCIEDADE SIMPLES LTDA | C48: 0 | F48: 45680
A49: F000047 | B49: Big Data Soluções em Tecnologia de Informatica SA | C49: 0 | E49: 19 | F49: 45791
A50: F000048 | B50: ABA SERVIÇOS DE TREINAMENTO E APRESENTAÇÃO LTDA | C50: 0 | F50: 45374
A51: F000049 | B51: YPO INC. | C51: 0 | F51: 45374
A52: F000050 | B52: AD AGENCIA DE VIAGENS E TURISMO LTDA - EPP | C52: 0 | F52: 45374
A53: F000051 | B53: Sandra Matsumoto Nakaoka Assessoria | C53: 0 | E53: 12 | F53: 45923
A54: F000052 | B54: DAS - CONSULTORIA FISCAL E FINANCEIRA LTDA | C54: 0 | F54: 45374
A55: F000053 | B55: VAINZOF, LIMA E KARASSAWA SOCIEDADE DE ADVOGADOS | C55: 0 | F55: 45374
A56: F000054 | B56: FOGO’S CHURRASCARIA LTDA | C56: 0 | F56: 45374
A57: F000055 | B57: FIGUEIRA PRODUÇOES ARTISTICAS EIRELLI | C57: 0 | F57: 46105
A58: F000056 | B58: STS CONSULTORIA EMPRESARIAL LTDA | C58: 0 | F58: 45374
A59: F000057 | B59: Boardvantage, Inc | C59: 0 | F59: 45374
A60: F000058 | B60: CARECA EVENTOS E PROMOÇÕES LTDA | C60: 0 | F60: 45374
A61: F000059 | B61: CEAN CARLOS SILVA COSTA | C61: 0 | F61: 45374
A62: F000060 | B62: RESTAURANTE BACALHAU E VINHO DO ITAIM LTDA. | C62: 0 | F62: 45890
A63: F000061 | B63: GITHUB, INC | C63: 0 | F63: 45286
A64: F000062 | B64: Otavio Augusto Gomes de Araujo | C64: 0 | F64: 45302
A65: F000063 | B65: WeWork Serviços de Escritório Ltda. | C65: 0 | E65: 12 | F65: 45791
A66: F000064 | B66: Fingage Negócios e Soluções LTDA | C66: 0 | F66: 45706
A67: F000065 | B67: LABEO FINANCE CONSULTORIA EMPRESARIAL LTDA | C67: 0 | F67: 45695
A68: F000066 | B68: Rodrigo Ferreira Costa | C68: -22 | E68: 12 | F68: 45791
A69: F000067 | B69: FREITAS FERRAZ CAPURUCO BRAICHI RICCIO SOCIEDADE DE ADVOGADOS | C69: 0 | F69: 45356
A70: F000068 | B70: CENTRO DE ESTAGIOS - PPM HUMAN RESOURCES LTDA | C70: 0 | F70: 45757
A71: F000069 | B71: VCS GESTAO EM NEGOCIOS LTDA | C71: -209 | E71: 12 | F71: 45791
A72: F000070 | B72: NH SOLUTION MARKET LTDA | C72: 0 | F72: 45427
A73: F000071 | B73: INVENT SOFTWARE LTDA | C73: -24751.76 | E73: 19 | F73: 45791
A74: F000072 | B74: iDeals Do Brasil Servicos De Informacao LTDA. | C74: 0 | E74: 19 | F74: 46055
A75: F000073 | B75: RCM SOLUCOES EM GESTAO EMPRESARIAL LTDA | C75: 0 | F75: 45596
A76: F000074 | B76: NO CONTROLE CONSULTING LTDA | C76: 0 | F76: 45497
A77: F000075 | B77: RENTAL- BUS LOCACOES E EVENTOS LTDA | C77: 0 | F77: 45519
A78: F000076 | B78: WKG Servicos Administrativos Ltda | C78: 0 | F78: 45526
A79: F000077 | B79: REDASSET GESTAO DE RECURSOS LTDA | C79: 0 | E79: 12 | F79: 45791
A80: F000078 | B80: Sulamerica Companhia de seguro saude | C80: 0 | E80: 16 | F80: 45791
A81: F000079 | B81: Alexandre Saddy Chade | C81: 0 | F81: 45569
A82: F000080 | B82: JUAN SEBASTIAN ARES PEREIRA | C82: 0 | F82: 45574
A83: F000081 | B83: ASCET REALTY ADMINISTRADORA DE BENS LTDA. | C83: 0 | F83: 45580
A84: F000082 | B84: BR PARTNERS ASSESSORIA FINANCEIRA LTDA | C84: 0 | E84: 12 | F84: 45831
A85: F000083 | B85: RED FUNDO DE INVESTIMENTO EM DIREITOS CREDITORIOS REAL LP DE RESPONSABILIDADE LIMITADA | C85: 0 | E85: 12 | F85: 45791
A86: F000084 | B86: BEST - BRAZIL ENGAGEMENT SERVICES AND TRAINING LTDA. | C86: 0 | E86: 12 | F86: 45791
A87: F000085 | B87: COMPANHIA BRASILEIRA DE SERVIÇOS DE MARKETING | C87: -30 | E87: 12 | F87: 45791
A88: F000086 | B88: Tania Cardozo da Costa | C88: 0 | F88: 45680
A89: F000087 | B89: Jéssica de Paula Uchôas Papini | C89: 0 | F89: 45680
A90: F000088 | B90: Cristiano Monteiro Cardoso | C90: 0 | F90: 45680
A91: F000089 | B91: William Abreu de Souza | C91: 0 | F91: 45680
A92: F000090 | B92: Fabiana Vilhena Venditti | C92: 0 | F92: 46034
A93: F000091 | B93: ANA BEATRIZ PINHEIRO GUERRA | C93: 0 | F93: 46034
A94: F000092 | B94: E J DENTELLO SERVICOS ADMINISTRATIVOS LTDA | C94: 0 | F94: 45687
A95: F000093 | B95: Isabela Ribeiro Vaz Alves | C95: 0 | F95: 45692
A96: F000094 | B96: VORTX SERVICOS FIDUCIARIOS LTDA. | C96: -885.45 | E96: 12 | F96: 45791
A97: F000095 | B97: INTERACAO AUTOMACAO E COMERCIO | C97: 0 | F97: 45744
A98: F000096 | B98: SLP CONSULTORIA E TREINAMENTO LTDA ME | C98: 0 | E98: 12 | F98: 45923
A99: F000097 | B99: PROTEA CONSULTORIA LTDA | C99: 0 | E99: 12 | F99: 45923
A100: F000098 | B100: Casa Coworking Apoio Admiministrativo Ltda-ME | C100: 0 | E100: 12 | F100: 45995
...

Sheet noverdefornecedor
A1: Código do PN | B1: Nome do PN | C1: Moeda do PN | D1: Saldo da conta | E1: Endereço de cobrança padrão | F1: Endereço de cobrança: cidade | G1: Endereço de cobrança: distrito | H1: Endereço de cobrança: país/região | I1: CNPJ/CPF | J1: [Act]-Item Fluxo de Caixa | K1: Data de atualização
A2: C000001 | B2: QI SOCIEDADE DE CREDITO DIRETO S.A.
A3: C000002 | B3: FUNDO DE INVESTIMENTO EM DIREITOS CREDIT EMPIRICA NOVERDE CRED PESSOAL
A4: C000003 | B4: RIZA NOVERDE CDC - FUNDO DE INVESTIMENTO EM DIREITOS CREDITORIOS
A5: C000004 | B5: SUPERSIM ANALISE DE DADOS E CORRESPONDENTE BANCARIO LTDA.
A6: C000005 | B6: BMP SOCIEDADE DE CREDITO DIRETO S.A
A7: C000006 | B7: BANCO DIGIO S.A.
A8: C000007 | B8: ZURICH MINAS BRASIL SEGUROS S.A.
A9: C000008 | B9: REDE MAIS SAUDE LTDA
A10: C000009 | B10: ZURICH MINAS BRASIL SEGUROS S.A.
A11: C000010 | B11: JEITTO INSTITUICAO DE PAGAMENTO LTDA
A12: C000011 | B12: LH1010 SERVICOS CORRESPONDENTE BANCARIO LTDA
A13: C000012 | B13: DOTZFIN FUNDO DE INVESTIMENTO EM DIREITOS CREDITORIOS-RESPONSABILIDADE LTDA
... A226: LC00009 | B226: FIDC - PERDA OPERACIONAL

Sheet payfornecedor
A1: Código do PN | B1: Nome do PN | C1: Saldo da conta | D1: [Act]-Item Fluxo de Caixa | E1: Data de atualização
A2: 2021001 | B2: TECH AND SOUL COMUNICACAO E MARKETING LTDA | C2: 0
A3: C202201 | B3: CREDISFERA SERVICOS FINANCEIROS LTDA | C3: 0 | D3: 44 | E3: 45791
A4: C202202 | B4: DOCK INSTITUICAO DE PAGAMENTO S.A. | C4: 1847.42 | D4: 44 | E4: 45791
A5: C202203 | B5: PROVU SERVICOS DE ADMINISTRACAO E CORRESPONDENTE BANCARIO S.A. | C5: 0 | D5: 44 | E5: 45791
A6: C202204 | B6: ELO SERVICOS S.A. | C6: 0 | D6: 44 | E6: 45791
A7: C202205 | B7: COMPANHIA GLOBAL DE SOLUCOES E SERVICOS DE PAGAMENTOS S.A. | C7: 0 | D7: 44 | E7: 46084
A8: C202206 | B8: NOVERDE TECNOLOGIA E PAGAMENTOS S/A | C8: 0 | D8: 44 | E8: 45791
A9: C202207 | B9: PANDURATA ALIMENTOS LTDA | C9: 0 | D9: 44 | E9: 45791
A10: C2023001 | B10: TELEFONICA BRASIL S.A. | C10: 0 | D10: 44 | E10: 45791
A11: C2023002 | B11: QI SOCIEDADE DE CREDITO DIRETO S.A. | C11: 0 | D11: 44 | E11: 46058
A12: C2024001 | B12: SAVEGNAGO SUPERMERCADOS LTDA | C12: 7124.72 | D12: 44 | E12: 45791
A13: C2025001 | B13: CBSM | C13: 0 | D13: 44 | E13: 45791
A14: C2025002 | B14: Drift comercio de alimentos S/A | C14: 1050.23 | D14: 44 | E14: 46044
... A17: F000001 | B17: DOCK TECNOLOGIA S.A. | C17: 0 | D17: 56 | E17: 45791
A18: F000002 | B18: MARCO ANTONIO VIEIRA ARTES GRAFICAS E BRINDES | C18: 0 | E18: 45769
A19: F000003 | B19: PREFEITURA DE SÃO PAULO | C19: 0 | E19: 43663
A20: F000004 | B20: Paysmart Pagamentos Eletronicos LTDA | C20: 0
A21: F000005 | B21: DOCK SOLUÇÕES EM MEIOS DE PAGAMENTO S.A. | C21: 0 | D21: 56 | E21: 45791
A22: F000006 | B22: TAISSA ANDRADE STERIM 03563873720 | C22: 0 | E22: 43923
A23: F000007 | B23: Getnet Adquirência e Serviços para Meios de Pagamento S/A | C23: 0
A24: F000008 | B24: FISERV DO BRASIL INSTITUICAO DE PAGAMENTO LTDA | C24: 0 | D24: 56 | E24: 45791
A25: F000009 | B25: STILGRAF ARTES GRAFICAS E EDITORA LTDA | C25: 0 | D25: 51 | E25: 45791
A26: F000010 | B26: EYXO ESTRATÉGIAS DE INOVAÇÃO LTDA | C26: 0
A27: F000011 | B27: ELO SERVIÇOS S.A. | C27: -350 | D27: 56 | E27: 45791
A28: F000012 | B28: LSJ SERVICES MANUTENCAO DE INFORMATICA LTDA | C28: 0
A29: F000013 | B29: VALID SOLUCOES S.A | C29: 0
A30: F000014 | B30: BRASPAG-TECNOLOGIA EM PAGAMENTO LTDA | C30: 0
A31: F000015 | B31: BIG DATA SOLUCOES EM TECNOLOGIA DE INFORMATICA LTDA | C31: 0 | D31: 56 | E31: 45791
A32: F000016 | B32: LABSIT INTELIGENCIA DIGITAL LTDA | C32: 0 | D32: 56 | E32: 45791
A33: F000017 | B33: CBSM COMPANHIA BRASILEIRA DE SOLUÇÕES DE MARKETING S/A | C33: 0 | D33: 51 | E33: 45985
A34: F000018 | B34: VITRIO CONSULTORIA LTDA | C34: 0 | E34: 44362
A35: F000019 | B35: RSM BPS SP SERVIÇOS CONTABEIS SOCIEDADE SIMPLES LTDA | C35: 0 | E35: 45374
A36: F000020 | B36: D & F LOGÍSTICA DISTRIBUIÇÃO E SERVIÇOS LTDA | C36: 0 | D36: 56 | E36: 45791
A37: F000021 | B37: ACERT ID- SERVIÇOS DE TECNOLOGIA E TREINAMENTO | C37: 0
A38: F000022 | B38: WORK E COMPANY DESIGN DE PRODUTO DIGITAL LTDA. | C38: 0
A39: F000023 | B39: COM PASSO EXTERIOR LTDA | C39: 0
A40: F000024 | B40: FIGUEIRA PRODUÇOES ARTISTICAS EIRELI | C40: 0
A41: F000025 | B41: Maíra Arthur Sampaio Antonácio – ME | C41: 0
A42: F000026 | B42: GRAFICA E EDITORA PIFFERPRINT LTDA | C42: 0
A43: F000027 | B43: THALES DIS BRASIL CARTOES E SOLUCOES DE TECNOLOGIA LTDA. | C43: 0 | E43: 45374
A44: F000028 | B44: QUANTUM STRATEGICS CONSULTORIA E GESTAO EMPRESARIAL LTDA | C44: 0
A45: F000029 | B45: MARCIO MOTO EXPRESS EIRELI ME | C45: 0
A46: F000030 | B46: PLANO CDE ELOHIM CONSULTORIA E PESQUISA LTDA | C46: 0
A47: F000031 | B47: PROCOMP INDUSTRIA ELETRONICA LTDA | C47: 0
A48: F000032 | B48: PREMIUMGRAF SERVICOS GRAFICOS EIRELI | C48: 0
A49: F000033 | B49: PINHEIRO NETO ADVOGADOS | C49: -86831.93 | D49: 51 | E49: 45791
A50: F000034 | B50: ALEXANDRE PIRES DA SILVA | C50: 0
A51: F000035 | B51: MAGAZINE LUIZA S/A | C51: 0
A52: F000036 | B52: TECH AND SOUL COMUNICACAO E MARKETING LTDA | C52: 0
A53: F000037 | B53: RODOMINAS ENCOMENDAS LTDA | C53: 0 | E53: 44020
A54: F000038 | B54: LOCOMOTIVA CONSULTORIA, MARKETING E NEGOCIOS EMERGENTES LTDA | C54: 0
A55: F000039 | B55: LOGGI TECNOLOGIA LTDA | C55: 0
A56: F000040 | B56: CENTRO DE DISTRIBUICAO DE TITULOS E DOCUMENTOS DE SAO PAULO - CDT | C56: 0
A57: F000041 | B57: DISTRIBUIDORA DE JORNAIS E PERIODICOS LTDA | C57: 0
A58: F000042 | B58: MINHA AUTORIA ASSESSORIA EM DIREITOS MUSICAIS LTDA | C58: 0
A59: F000043 | B59: COMPANHIA GLOBAL DE SOLUCOES E SERVICOS DE PAGAMENTOS S.A. | C59: -226.68 | D59: 51 | E59: 45791
A60: F000044 | B60: DOUGLAS GESSER | C60: 0
A61: F000045 | B61: PULCOR INDUSTRIA E COMERCIO DE PRODUTOS PARA IDENTIFICACAO LTDA | C61: 0
A62: F000046 | B62: LAB MOTION VIDEOS LTDA | C62: 0
A63: F000047 | B63: SANTA PRODUCAO DE FILMES EIRELI | C63: 0
A64: F000048 | B64: OTAVIO DE MORAES PRODUCOES ARTISTICAS LTDA | C64: 0
A65: F000049 | B65: LABORPRINT GRAFICA E EDITORA EIRELI | C65: 0
A66: F000050 | B66: ACOA ASSESSORIA E CONSULTORIA EMPRESARIAL LTDA. | C66: 0
A67: F000051 | B67: FACEBOOK SERVICOS ONLINE DO BRASIL LTDA. | C67: 0 | E67: 45374
A68: F000052 | B68: GOOGLE BRASIL INTERNET LTDA. | C68: 0 | D68: 56 | E68: 45791
A69: F000053 | B69: CONCIL INTELIGENCIA EM CONCILIACAO S.A. | C69: 0 | E69: 45374
A70: F000054 | B70: SCERTUS CONSULTORIA LTDA | C70: 0
A71: F000055 | B71: MOTO PRIME EXPRESS LOGISTICA LTDA | C71: 0
A72: F000056 | B72: RANKMYAPP SOFTWARE E SERVICOS DE INTERNET S.A. | C72: 0 | E72: 45374
A73: F000057 | B73: TAGGPROMO TRABALHOS TEMPORARIOS LTDA | C73: 0
A74: F000058 | B74: OLIVER WYMAN CONSULTORIA EM ESTRATEGIA DE NEGOCIOS LTDA. | C74: 0
A75: F000059 | B75: OPAH IT CONSULTING DESENVOLVIMENTO DE SISTEMAS LTDA | C75: 0 | E75: 45374
A76: F000060 | B76: EMERGENCY DOCUMENTACAO IMOBILIARIA EIRELI | C76: 0
A77: F000061 | B77: C C FERREIRA FRANCA | C77: 0
A78: F000062 | B78: A2 SERVICOS GRAFICOS E COMERCIO LTDA | C78: 0
A79: F000063 | B79: PROFIC ACCOUNTING & CONSULTING LTDA | C79: 0 | E79: 45374
A80: F000064 | B80: D & F LOGISTICA DISTRIBUICAO E SERVICOS LTDA | C80: -3443 | D80: 56 | E80: 45791
A81: F000065 | B81: CURIEL DESIGN SERVICOS DE INFORMATICA LTDA | C81: 0
A82: F000066 | B82: APPLIFT VEICULACAO DE PUBLICIDADE NA INTERNET LTDA. | C82: 0 | E82: 44193
A83: F000067 | B83: E S Z COMUNICACAO LTDA. | C83: 0
A84: F000068 | B84: BANCO BTG PACTUAL S.A. | C84: 0 | D84: 51 | E84: 46028
A85: F000069 | B85: TK COMUNICACAO VISUAL EIRELI | C85: 0
A86: F000070 | B86: COMPASSO TECNOLOGIA LTDA. | C86: 0 | E86: 45374
A87: F000071 | B87: ECONOMAPAS SISTEMAS E TECNOLOGIA LTDA | C87: 0
A88: F000072 | B88: TPZ SOLUCOES DIGITAIS LTDA. | C88: -56818.74 | D88: 56 | E88: 45905
A89: F000073 | B89: FOCACCIA, AMARAL E LAMONICA SOCIEDADE DE ADVOGADOS | C89: 0 | D89: 51 | E89: 45791
A90: F000074 | B90: REAL SRR SP PUBLICIDADE E MARKETING LTDA. | C90: 0 | D90: 51 | E90: 46048
A91: F000075 | B91: IDEMIA DO BRASIL - SOLUCOES E SERVICOS DE TECNOLOGIA LTDA | C91: -634.97 | D91: 56 | E91: 45933
A92: F000076 | B92: VCS CERTIFICACAO E SERVICOS LTDA | C92: -200 | E92: 45374
A93: F000077 | B93: FABRICIO KAEMMERER BRENNER 02821244037 | C93: 0
A94: F000078 | B94: THALES DIS BRASIL CARTOES E SOLUCOES DE TECNOLOGIA LTD | C94: 0
A95: F000079 | B95: TAGGPROMO MARKETING PROMOCIONAL LTDA | C95: 0
A96: F000080 | B96: MANUCCI ADVOGADOS | C96: 0
A97: F000081 | B97: FCAMARA CONSULTORIA E FORMACAO EM INFORMATICA LTDA | C97: 0 | E97: 45374
A98: F000082 | B98: DEXTRA TECNOLOGIA S/A | C98: 0
A99: F000083 | B99: CI&T SOFTWARE S/A | C99: 0 | E99: 44655
A100: F000084 | B100: KRYPTONPAY GESTAO DE RECEBIVEIS E PAGAMENTOS LTDA | C100: 0
A101: F000085 | B101: Marco Antonio Vieira | C101: 0 | E101: 45374
A102: F000086 | B102: PRICEWATERHOUSECOOPERS CORPORATE FINANCE & RECOVERY LTDA | C102: 0 | E102: 45374
...

Sheet BaseConsol
A1: Empresa | B1: Mês/Ano | C1: Nº transação | D1: Ref.3 | E1: Conta contábil | F1: Fornecedor | G1: SubGrupo | H1: Valor | I1: Descrição Conta | J1: SubLimpo
A2: {=_xlfn.LET(_xlpm.b,_xlfn.VSTACK(_xlfn.HSTACK(CBSMprovisões!M3:M200,CBSMprovisões!L3:L200,CBSMprovisões!B3:B200,CBSMprovisões!E3:E200,CBSMprovisões!F3:F200,CBSMprovisões!J3:J200,CBSMprovisões!K3:K200,CBSMprovisões!H3:H200,CBSMprovisões!N3:N200),_xlfn.HSTACK(Noverdeprovisões!M3:M200,Noverdeprovisões!L3:L200,Noverdeprovisões!B3:B200,Noverdeprovisões!E3:E200,Noverdeprovisões!F3:F200,Noverdeprovisões!J3:J200,Noverdeprovisões!K3:K200,Noverdeprovisões!H3:H200,Noverdeprovisões!N3:N200),_xlfn.HSTACK(Dotzprovisões!M3:M200,Dotzprovisões!L3:L200,Dotzprovisões!B3:B200,Dotzprovisões!E3:E200,Dotzprovisões!F3:F200,Dotzprovisões!J3:J200,Dotzprovisões!K3:K200,Dotzprovisões!H3:H200,Dotzprovisões!N3:N200),_xlfn.HSTACK(PAYprovisões!M3:M200,PAYprovisões!L3:L200,PAYprovisões!B3:B200,PAYprovisões!E3:E200,PAYprovisões!F3:F200,PAYprovisões!J3:J200,PAYprovisões!K3:K200,PAYprovisões!H3:H200,PAYprovisões!N3:N200)),_xlfn._xlws.FILTER(_xlpm.b,INDEX(_xlpm.b,0,1)<>""))} -> CBSM | B2: 45992 | C2: 8635611 | D2: F009096 | E2: 3313030 | F2: KRAKOWIAK ADVOGADOS | G2: Services | H2: -242060 | I2: Assessoria Jurídica | J2: {=IF(INDEX(_xlfn.ANCHORARRAY(A2),0,7)="","(Sem subgrupo)",INDEX(_xlfn.ANCHORARRAY(A2),0,7))} -> Services
A3: CBSM | B3: 45992 | C3: 8635623 | D3: F009582 | E3: 3313350 | F3: MENA INTELIGENCIA EM TALENTOS LTDA | G3: Services | H3: -10000 | I3: Serviços de Consultoria | J3: Services
A4: CBSM | B4: 46023 | C4: 8652891 | D4: F008870 | E4: 3313160 | F4: PARLA CONTAC CENTER S/A | G4: CRM & Call Center | H4: -24000 | I4: Despesas Call Center | J4: CRM & Call Center
A5: CBSM | B5: 46054 | C5: 8655981 | D5: F009582 | E5: 3313350 | F5: MENA INTELIGENCIA EM TALENTOS LTDA | G5: Services | H5: 3551.56 | I5: Serviços de Consultoria | J5: Services
A6: CBSM | B6: 46054 | C6: 8669549 | D6: F008870 | E6: 3313160 | F6: PARLA CONTAC CENTER S/A | G6: CRM & Call Center | H6: -24000 | I6: Despesas Call Center | J6: CRM & Call Center
A7: CBSM | B7: 46082 | C7: 8686394 | D7: F008408 | E7: 3313160 | F7: 55TELECOM COMUNICAÇÃO LTDA | G7: CRM & Call Center | H7: -33100 | I7: Despesas Call Center | J7: CRM & Call Center
A8: CBSM | B8: 46113 | C8: 8702918 | D8: F005535 | E8: 3211020 | F8: INFOBIP BRAZIL SERVICOS DE VALOR ADICIONADO LTDA. | G8: Other costs - CBSM CAT | H8: -78757.99 | I8: CAT - Gastos com tecnologia | J8: Other costs - CBSM CAT
A9: CBSM | B9: 46113 | C9: 8702919 | D9: F005535 | E9: 3211020 | F9: INFOBIP BRAZIL SERVICOS DE VALOR ADICIONADO LTDA. | G9: Other costs - CBSM CAT | H9: -45331.47 | I9: CAT - Gastos com tecnologia | J9: Other costs - CBSM CAT
A10: CBSM | B10: 46143 | C10: 8718557 | D10: F006557 | E10: 3313030 | F10: MOSS, MUZZI, FALCAO, MASSOTE E WERNECK ADVOGADOS ASSOCIADOS | G10: Services | H10: -59573.47 | I10: Assessoria Jurídica | J10: Services
A11: CBSM | B11: 46143 | C11: 8719033 | D11: F009633 | E11: 3313160 | F11: CSU DIGITAL | G11: CRM & Call Center | H11: -58405.53 | I11: Despesas Call Center | J11: CRM & Call Center
A12: CBSM | B12: 46143 | C12: 8719034 | D12: F008408 | E12: 3313160 | F12: 55TELECOM COMUNICAÇÃO LTDA | G12: CRM & Call Center | H12: -8847.57 | I12: Despesas Call Center | J12: CRM & Call Center
A13: CBSM | B13: 46143 | C13: 8719035 | D13: F008547 | E13: 3313161 | F13: QUEST TECNOLOGIA LTDA | G13: CRM & Call Center | H13: -10500 | I13: Pesquisa | J13: CRM & Call Center
A14: CBSM | B14: 46143 | C14: 8719036 | D14: F001362 | E14: 3313160 | F14: OBVIO BRASIL SOFTWARE E SERVICOS LTDA | G14: CRM & Call Center | H14: -18000 | I14: Despesas Call Center | J14: CRM & Call Center
... A64: Dotz | B64: 46023 | C64: 15276 | D64: F000166 | E64: 3313020 | F64: GRANT THORNTON AUDITORES INDEPENDENTES LTDA | G64: Services | H64: -34013.61 | I64: Assessoria Contábil | J64: Services
A65: Dotz | B65: 46054 | C65: 15573 | D65: F000036 | E65: 2111004 | F65: Pinheiro Guimarães | H65: -8449.78 | J65: (Sem subgrupo)
A66: Dotz | B66: 46054 | C66: 15453 | D66: F000166 | E66: 3313020 | F66: GRANT THORNTON AUDITORES INDEPENDENTES LTDA | G66: Services | H66: -34013.61 | I66: Assessoria Contábil | J66: Services
A67: Dotz | B67: 46082 | C67: 15996 | D67: F000166 | E67: 3313020 | F67: GRANT THORNTON AUDITORES INDEPENDENTES LTDA | G67: Services | H67: -34013.61 | I67: Assessoria Contábil | J67: Services
A68: Dotz | B68: 46113 | C68: 16363 | D68: F000165 | E68: 3313350 | F68: HEIDRICK & STRUGGLES RECRUTAMENTO ESPECIALIZADO LTDA. | G68: Services | H68: -61980.91 | I68: Serviços de Consultoria | J68: Services
A69: Dotz | B69: 46143 | C69: 16774 | D69: F000103 | E69: 3313030 | F69: Mello e Torres Sociedade de Advogados | G69: Services | H69: -41743.92 | I69: Assessoria Jurídica | J69: Services
A70: Dotz | B70: 46143 | C70: 16775 | D70: F000165 | E70: 3313350 | F70: HEIDRICK & STRUGGLES RECRUTAMENTO ESPECIALIZADO LTDA. | G70: Services | H70: -61980.91 | I70: Serviços de Consultoria | J70: Services
A71: Dotz | B71: 46143 | C71: 16809 | D71: F000166 | E71: 3313020 | F71: GRANT THORNTON AUDITORES INDEPENDENTES LTDA | G71: Services | H71: -34013.61 | I71: Assessoria Contábil | J71: Services
A72: Dotz | B72: 46143 | C72: 16818 | D72: F000023 | E72: 3313350 | F72: ACTION SYSTEMS SERVICOS EM INFORMATICA LTDA | G72: Services | H72: -9576.28 | I72: Serviços de Consultoria | J72: Services
A73: Dotz | B73: 46143 | C73: 16819 | D73: F000071 | E73: 3313270 | F73: INVENT SOFTWARE LTDA | G73: IT & Telecom | H73: -18750 | I73: Licenças | J73: IT & Telecom
A74: Dotz | B74: 46143 | C74: 16745 | D74: F000163 | E74: 3313030 | F74: MOSS, MUZZI, FALCAO, MASSOTE E WERNECK ADVOGADOS ASSOCIADOS | G74: Services | H74: -21404.25 | I74: Assessoria Jurídica | J74: Services
A75: PAY | B75: 46054 | C75: 43065 | D75: F000119 | E75: 81763005002 | F75: GRANT THORNTON AUDITORES INDEPENDENTES LTDA | G75: Services | H75: -5833.33 | I75: Assessoria Contábil e Auditoria | J75: Services
A76: PAY | B76: 46082 | C76: 43819 | D76: F000119 | E76: 81763005002 | F76: GRANT THORNTON AUDITORES INDEPENDENTES LTDA | G76: Services | H76: -5833.33 | I76: Assessoria Contábil e Auditoria | J76: Services
A77: PAY | B77: 46113 | C77: 44280 | D77: F000119 | E77: 81763005002 | F77: GRANT THORNTON AUDITORES INDEPENDENTES LTDA | G77: Services | H77: -5833.33 | I77: Assessoria Contábil e Auditoria | J77: Services
A78: PAY | B78: 46143 | C78: 44823 | D78: F000072 | E78: 81739008007 | F78: TPZ SOLUCOES DIGITAIS LTDA. | G78: Other costs - Dotz Pay | H78: -57307 | I78: Onboarding | J78: Other costs - Dotz Pay

Sheet Dashboard
B1: ="Visão Geral — Provisões "&IF($C$3="Todos","(Consolidado)",$C$3) -> Visão Geral — Provisões (Consolidado) | J1: Dashboard | K1: Relatório | N1: Mês | O1: Total | Q1: SubGrupo | R1: Total | V1: =MAX(_xlfn.ANCHORARRAY(R2)) -> 3422803.4 | W1: =IF($C$3="Todos","<>",$C$3) -> <> | AA1: Todos | AB1: Todos | AC1: Todos | AJ1: Empresa | AK1: Total
C2: Filtro Empresa | E2: Total Provisionado | N2: {=IFERROR(_xlfn._xlws.SORT(_xlfn.UNIQUE(_xlfn._xlws.FILTER(BaseConsol!$B$2:$B$400,(BaseConsol!$A$2:$A$400<>"")*((BaseConsol!$A$2:$A$400=$C$3)+($C$3="Todos")>0)))),"")} -> 45962 | O2: {=-SUMIFS(BaseConsol!$H$2:$H$400,BaseConsol!$A$2:$A$400,$W$1,BaseConsol!$B$2:$B$400,_xlfn.ANCHORARRAY(N2))} -> 30000 | Q2: {=IFERROR(_xlfn._xlws.SORT(_xlfn.UNIQUE(_xlfn._xlws.FILTER(BaseConsol!$J$2:$J$400,(BaseConsol!$A$2:$A$400<>"")*((BaseConsol!$A$2:$A$400=$C$3)+($C$3="Todos")>0)))),"")} -> (Sem subgrupo) | R2: {=-SUMIFS(BaseConsol!$H$2:$H$400,BaseConsol!$A$2:$A$400,$W$1,BaseConsol!$J$2:$J$400,_xlfn.ANCHORARRAY(Q2))} -> 8449.78 | T2: {=IFERROR(_xlfn._xlws.SORT(_xlfn.HSTACK(_xlfn.ANCHORARRAY(Q2),_xlfn.ANCHORARRAY(R2)),2,-1),"")} -> Other costs - NoVerde | U2: 3422803.4 | W2: <> | AA2: {=_xlfn._xlws.SORT(_xlfn.UNIQUE(_xlfn._xlws.FILTER(BaseConsol!$A$2:$A$400,BaseConsol!$A$2:$A$400<>"")))} -> CBSM | AB2: {=_xlfn._xlws.SORT(_xlfn.UNIQUE(_xlfn._xlws.FILTER(BaseConsol!$J$2:$J$400,BaseConsol!$J$2:$J$400<>"")))} -> (Sem subgrupo) | AC2: {=TEXT(_xlfn._xlws.SORT(_xlfn.UNIQUE(_xlfn._xlws.FILTER(BaseConsol!$B$2:$B$400,BaseConsol!$B$2:$B$400<>""))),"mmm/aa")} -> nov/25 | AJ2: {=IFERROR(_xlfn._xlws.SORT(_xlfn.UNIQUE(_xlfn._xlws.FILTER(BaseConsol!$A$2:$A$400,(BaseConsol!$A$2:$A$400<>"")*((BaseConsol!$A$2:$A$400=$C$3)+($C$3="Todos")>0)))),"")} -> CBSM | AK2: {=IFERROR(-SUMIF(BaseConsol!$A$2:$A$400,_xlfn.ANCHORARRAY(AJ2),BaseConsol!$H$2:$H$400),"")} -> 1358729.6 | AM2: {=_xlfn.LET(_xlpm.f,_xlfn.UNIQUE(_xlfn._xlws.FILTER(BaseConsol!$F$2:$F$400,(BaseConsol!$A$2:$A$400<>"")*((BaseConsol!$A$2:$A$400=$C$3)+($C$3="Todos")>0))),_xlpm.v,-SUMIFS(BaseConsol!$H$2:$H$400,BaseConsol!$F$2:$F$400,_xlpm.f,BaseConsol!$A$2:$A$400,$W$1),_xlfn.TAKE(_xlfn._xlws.SORT(_xlfn.HSTACK(_xlpm.f,_xlpm.v),2,-1),10))} -> BOA VISTA SERVICOS S.A. | AN2: 937219.22
C3: Todos | E3: =-SUMIFS(BaseConsol!$H$2:$H$400,BaseConsol!$A$2:$A$400,$W$1) -> 5985578.5 | N3: 45992 | O3: 282060 | Q3: CRM & Call Center | R3: 504279.51 | T3: Services | U3: 672011.87 | W3: <> | AA3: Dotz | AB3: CRM & Call Center | AC3: dez/25 | AJ3: Dotz | AK3: 359940.49 | AM3: SERASA S.A | AN3: 706969.61
N4: 46023 | O4: 359413.61 | Q4: Financial Losses over Cyber attacks | R4: 600000 | T4: Financial Losses over Cyber attacks | U4: 600000 | AA4: Noverde | AB4: Financial Losses over Cyber attacks | AC4: jan/26 | AJ4: Noverde | AK4: 4192101.4 | AM4: FIDC - PERDA OPERACIONAL | AN4: 600000
C5: Provisão por Empresa | H5: Provisão por Pacote Contábil | N5: 46054 | O5: 378745.16 | Q5: IT & Telecom | R5: 349944.05 | T5: CRM & Call Center | U5: 504279.51 | AA5: PAY | AB5: IT & Telecom | AC5: fev/26 | AJ5: PAY | AK5: 74806.99 | AM5: Gestora de Inteligência de Crédito S.A. | AN5: 550000
N6: 46082 | O6: 355642.88 | Q6: Other costs - CBSM CAT | R6: 370782.88 | T6: Other costs - CBSM CAT | U6: 370782.88 | AB6: Other costs - CBSM CAT | AC6: mar/26 | AM6: PONTAL SERVICOS EM COMUNICACAO DIGITAL LTDA | AN6: 450000
N7: 46113 | O7: 470303.7 | Q7: Other costs - Dotz Pay | R7: 57307 | T7: IT & Telecom | U7: 349944.05 | AB7: Other costs - Dotz Pay | AC7: abr/26 | AM7: INFOBIP BRAZIL SERVICOS DE VALOR ADICIONADO LTDA. | AN7: 370782.88
N8: 46143 | O8: 4109413.1 | Q8: Other costs - NoVerde | R8: 3422803.4 | T8: Other costs - Dotz Pay | U8: 57307 | AB8: Other costs - NoVerde | AC8: mai/26 | AM8: KRAKOWIAK ADVOGADOS | AN8: 242060
Q9: Services | R9: 672011.87 | T9: (Sem subgrupo) | U9: 8449.78 | AB9: Services | AM9: QUITE DIGITAL LTDA | AN9: 237459.15
AM10: CSU DIGITAL | AN10: 217186.94
AM11: GRANT THORNTON AUDITORES INDEPENDENTES LTDA | AN11: 153554.43
C18: Saldo de Provisão por Mês/Ano | H18: Provisões Top 10 Fornecedores
H19: =IFERROR(PROPER(INDEX(_xlfn.ANCHORARRAY($AM$2),1,1)),"") -> Boa Vista Servicos S.A. | K19: =IFERROR(INDEX(_xlfn.ANCHORARRAY($AM$2),1,2),"") -> 937219.22
H20: =IFERROR(PROPER(INDEX(_xlfn.ANCHORARRAY($AM$2),2,1)),"") -> Serasa S.A | K20: =IFERROR(INDEX(_xlfn.ANCHORARRAY($AM$2),2,2),"") -> 706969.61
H21: =IFERROR(PROPER(INDEX(_xlfn.ANCHORARRAY($AM$2),3,1)),"") -> Fidc - Perda Operacional | K21: =IFERROR(INDEX(_xlfn.ANCHORARRAY($AM$2),3,2),"") -> 600000
H22: =IFERROR(PROPER(INDEX(_xlfn.ANCHORARRAY($AM$2),4,1)),"") -> Gestora De Inteligência De Crédito S.A. | K22: =IFERROR(INDEX(_xlfn.ANCHORARRAY($AM$2),4,2),"") -> 550000
H23: =IFERROR(PROPER(INDEX(_xlfn.ANCHORARRAY($AM$2),5,1)),"") -> Pontal Servicos Em Comunicacao Digital Ltda | K23: =IFERROR(INDEX(_xlfn.ANCHORARRAY($AM$2),5,2),"") -> 450000
H24: =IFERROR(PROPER(INDEX(_xlfn.ANCHORARRAY($AM$2),6,1)),"") -> Infobip Brazil Servicos De Valor Adicionado Ltda. | K24: =IFERROR(INDEX(_xlfn.ANCHORARRAY($AM$2),6,2),"") -> 370782.88
H25: =IFERROR(PROPER(INDEX(_xlfn.ANCHORARRAY($AM$2),7,1)),"") -> Krakowiak Advogados | K25: =IFERROR(INDEX(_xlfn.ANCHORARRAY($AM$2),7,2),"") -> 242060
H26: =IFERROR(PROPER(INDEX(_xlfn.ANCHORARRAY($AM$2),8,1)),"") -> Quite Digital Ltda | K26: =IFERROR(INDEX(_xlfn.ANCHORARRAY($AM$2),8,2),"") -> 237459.15
H27: =IFERROR(PROPER(INDEX(_xlfn.ANCHORARRAY($AM$2),9,1)),"") -> Csu Digital | K27: =IFERROR(INDEX(_xlfn.ANCHORARRAY($AM$2),9,2),"") -> 217186.94
H28: =IFERROR(PROPER(INDEX(_xlfn.ANCHORARRAY($AM$2),10,1)),"") -> Grant Thornton Auditores Independentes Ltda | K28: =IFERROR(INDEX(_xlfn.ANCHORARRAY($AM$2),10,2),"") -> 153554.43

Sheet Relatorio Fornecedor
B1: Dashboard | D1: Relatório
B3: Relatório de Fornecedores
B4: ="Empresa: "&Dashboard!$C$3 -> Empresa: Todos
B6: Fornecedor | C6: Empresa | D6: Mês/Ano | E6: Ref.3 | F6: Descrição Conta | G6: Conta contábil | H6: Nº transação | I6: Valor
B7: {=IFERROR(_xlfn._xlws.SORT(_xlfn._xlws.FILTER(_xlfn.HSTACK(BaseConsol!$F$2:$F$400,BaseConsol!$A$2:$A$400,BaseConsol!$B$2:$B$400,BaseConsol!$D$2:$D$400,BaseConsol!$I$2:$I$400,BaseConsol!$E$2:$E$400,BaseConsol!$C$2:$C$400,BaseConsol!$H$2:$H$400),(BaseConsol!$A$2:$A$400<>"")*((BaseConsol!$A$2:$A$400=Dashboard!$C$3)+(Dashboard!$C$3="Todos")>0)),8,1),"Sem resultados")} -> FIDC - PERDA OPERACIONAL | C7: Noverde | D7: 46143 | E7: LC00009 | F7: Perdas Financeiras | G7: 81999006002 | H7: 20769 | I7: -600000
B8: Gestora de Inteligência de Crédito S.A. | C8: Noverde | D8: 46143 | E8: F000132 | F8: Custos de Credito | G8: 81763005006 | H8: 20724 | I8: -520000
B9: SERASA S.A | C9: Noverde | D9: 46023 | E9: F000072 | F9: Custo de Marketing (Custo) | G9: 81745009011 | H9: 18451 | I9: -271400
B10: BOA VISTA SERVICOS S.A. | C10: Noverde | D10: 46143 | E10: F000034 | F10: Custos de Credito | G10: 81763005006 | H10: 20725 | I10: -250000.01
B11: BOA VISTA SERVICOS S.A. | C11: Noverde | D11: 46054 | E11: F000034 | F11: Custos de Credito | G11: 81763005006 | H11: 18971 | I11: -250000
B12: PONTAL SERVICOS EM COMUNICACAO DIGITAL LTDA | C12: Noverde | D12: 46082 | E12: F000145 | F12: Custo de Cobrança (Custo) | G12: 81763005005 | H12: 19672 | I12: -250000
B13: BOA VISTA SERVICOS S.A. | C13: Noverde | D13: 46113 | E13: F000034 | F13: Custos de Credito | G13: 81763005006 | H13: 20161 | I13: -250000
B14: KRAKOWIAK ADVOGADOS | C14: CBSM | D14: 45992 | E14: F009096 | F14: Assessoria Jurídica | G14: 3313030 | H14: 8635611 | I14: -242060
B15: QUITE DIGITAL LTDA | C15: Noverde | D15: 46143 | E15: F000032 | F15: Custo de Cobrança (Custo) | G15: 81763005005 | H15: 20740 | I15: -237459.15
B16: SERASA S.A | C16: Noverde | D16: 46143 | E16: F000072 | F16: Custo de Cobrança (Custo) | G16: 81763005005 | H16: 20741 | I16: -224382.11
B17: SERASA S.A | C17: Noverde | D17: 46143 | E17: F000072 | F17: Custo de Marketing (Custo) | G17: 81745009011 | H17: 20733 | I17: -211187.5
B18: PONTAL SERVICOS EM COMUNICACAO DIGITAL LTDA | C18: Noverde | D18: 46143 | E18: F000145 | F18: Custo de Cobrança (Custo) | G18: 81763005005 | H18: 20739 | I18: -200000
B19: JB - AGENCIAMENTO DE SERVICOS E NEGOCIOS EM GERAL LTDA | C19: Noverde | D19: 46143 | E19: F000040 | F19: Custo de Marketing (Custo) | G19: 81745009011 | H19: 20735 | I19: -139857.5
... B75: 55TELECOM COMUNICAÇÃO LTDA | C75: CBSM | D75: 46143 | E75: F008408 | F75: Despesas Call Center | G75: 3313160 | H75: 8719034 | I75: -8847.57
B76: Pinheiro Guimarães | C76: Dotz | D76: 46054 | E76: F000036 | G76: 2111004 | H76: 15573 | I76: -8449.78
B77: LINKPARTNERS INFORMATION TECHNOLOGY TASI LTDA | C77: CBSM | D77: 46143 | E77: F006768 | F77: Suporte Técnico | G77: 3313380 | H77: 8719093 | I77: -8389.73
B78: GRANT THORNTON AUDITORES INDEPENDENTES LTDA | C78: PAY | D78: 46054 | E78: F000119 | F78: Assessoria Contábil e Auditoria | G78: 81763005002 | H78: 43065 | I78: -5833.33
B79: GRANT THORNTON AUDITORES INDEPENDENTES LTDA | C79: PAY | D79: 46082 | E79: F000119 | F79: Assessoria Contábil e Auditoria | G79: 81763005002 | H79: 43819 | I79: -5833.33
B80: GRANT THORNTON AUDITORES INDEPENDENTES LTDA | C80: PAY | D80: 46113 | E80: F000119 | F80: Assessoria Contábil e Auditoria | G80: 81763005002 | H80: 44280 | I80: -5833.33
B81: NEGOCIE AGORA SERVIÇOS E COBRANÇA LTDA | C81: Noverde | D81: 46113 | E81: F000159 | F81: Custo de Cobrança (Custo) | G81: 81763005005 | H81: 20177 | I81: -5400
B82: MOSS, MUZZI, FALCAO, MASSOTE E WERNECK ADVOGADOS ASSOCIADOS | C82: Noverde | D82: 46143 | E82: F000166 | F82: Assessoria Jurídica (Despesa) | G82: 81763005011 | H82: 20650 | I82: -653
B83: MENA INTELIGENCIA EM TALENTOS LTDA | C83: CBSM | D83: 46054 | E83: F009582 | F83: Serviços de Consultoria | G83: 3313350 | H83: 8655981 | I83: 3551.56
